Workbook

Sheet Overview
A4: System | B4: In-scope mean /21 | C4: Out-of-scope mean /15 | D4: Overall %
A5: System 1 v2 | B5: ='System 1 v2'!X27 -> 11 | C5: ='System 1 v2'!X28 -> 7.75 | D5: ='System 1 v2'!Y29 -> 0.52238095
A6: System 2 v2 | B6: ='System 2 v2'!X27 -> 14.25 | C6: ='System 2 v2'!X28 -> 10.5 | D6: ='System 2 v2'!Y29 -> 0.68285714
A7: System 3 v2 | B7: ='System 3 v2'!X27 -> 14.9375 | C7: ='System 3 v2'!X28 -> 11.25 | D7: ='System 3 v2'!Y29 -> 0.71904762
A8: System 4 v2 | B8: ='System 4 v2'!X27 -> 14.625 | C8: ='System 4 v2'!X28 -> 10.75 | D8: ='System 4 v2'!Y29 -> 0.70047619
A12: Multi-source & cross-topic synthesis | B12: Relevance | C12: Factual | D12: Grounding | E12: Synthesis | F12: Diversity | G12: Uncertainty | H12: Policy use
A13: System 1 v2 | B13: =AVERAGE('System 1 v2'!P6:P21) -> 1.875 | C13: =AVERAGE('System 1 v2'!Q6:Q21) -> 1.5625 | D13: =AVERAGE('System 1 v2'!R6:R21) -> 1.375 | E13: =AVERAGE('System 1 v2'!S6:S21) -> 1.375 | F13: =AVERAGE('System 1 v2'!T6:T21) -> 1.9375 | G13: =AVERAGE('System 1 v2'!U6:U21) -> 1.625 | H13: =AVERAGE('System 1 v2'!V6:V21) -> 1.25
A14: System 2 v2 | B14: =AVERAGE('System 2 v2'!P6:P21) -> 2 | C14: =AVERAGE('System 2 v2'!Q6:Q21) -> 2 | D14: =AVERAGE('System 2 v2'!R6:R21) -> 1.875 | E14: =AVERAGE('System 2 v2'!S6:S21) -> 1.9375 | F14: =AVERAGE('System 2 v2'!T6:T21) -> 2.5 | G14: =AVERAGE('System 2 v2'!U6:U21) -> 2.125 | H14: =AVERAGE('System 2 v2'!V6:V21) -> 1.8125
A15: System 3 v2 | B15: =AVERAGE('System 3 v2'!P6:P21) -> 2.75 | C15: =AVERAGE('System 3 v2'!Q6:Q21) -> 2 | D15: =AVERAGE('System 3 v2'!R6:R21) -> 1.875 | E15: =AVERAGE('System 3 v2'!S6:S21) -> 1.9375 | F15: =AVERAGE('System 3 v2'!T6:T21) -> 2.375 | G15: =AVERAGE('System 3 v2'!U6:U21) -> 2.1875 | H15: =AVERAGE('System 3 v2'!V6:V21) -> 1.8125
A16: System 4 v2 | B16: =AVERAGE('System 4 v2'!P6:P21) -> 2.0625 | C16: =AVERAGE('System 4 v2'!Q6:Q21) -> 1.9375 | D16: =AVERAGE('System 4 v2'!R6:R21) -> 1.8125 | E16: =AVERAGE('System 4 v2'!S6:S21) -> 2 | F16: =AVERAGE('System 4 v2'!T6:T21) -> 2.75 | G16: =AVERAGE('System 4 v2'!U6:U21) -> 2.1875 | H16: =AVERAGE('System 4 v2'!V6:V21) -> 1.875
A20: System | B20: Mean words | C20: Within 150 limit | D20: Mean seconds | E20: Total cost | F20: Fabricated citations | G20: average doc cited per answer
A21: System 1 v2 | B21: 320 | C21: 0/20 | D21: 30.9 | E21: free | F21: 6 | G21: 3.6
A22: System 2 v2 | B22: 180 | C22: 1/20 | D22: 2.1 | E22: $0.12 | F22: 0 | G22: 4.2
A23: System 3 v2 | B23: 143 | C23: 16/20 | D23: 35.1 | E23: $0.27 | F23: 0 | G23: 4.1
A24: System 4 v2 | B24: 184 | C24: 1/20 | D24: 6.6 | E24: $0.27 | F24: 0 | G24: 5.3

Sheet System 1 v2
A1: System 1 v2
F4: EXPECTED EVIDENCE | I4: WHAT THE SYSTEM DID | P4: SCORING
A5: Q ID | B5: Category | C5: Difficulty | D5: Topic area | E5: Question | F5: Expected corpus documents | G5: Expected uncertainty / disagreement | H5: Expected good behaviour | I5: Retrieved chunk IDs | J5: Invalid citations | K5: Words | L5: Seconds | M5: In tokens | N5: Out tokens | O5: Cost (USD) | P5: R | Q5: F | R5: G | S5: S | T5: D | U5: U | V5: P | W5: Out of | X5: Total | Y5: % | Z5: Scoring comments | AA5: Actual system output | AB5: Paid tokens | AC5: Audit run ID
A6: Q01 | B6: Direct evidence retrieval | C6: Easy | D6: Sources / emissions | E6: What are the main sources of atmospheric microplastics and which should be considered when considering emission-reduction policy interventions? | F6: DOC003,DOC002 DOC55DOC45 DOC52 DOC038 DOC05 DOC011 DOC29 | G6: Ther is some ambiguaty between parctile cizing as there is no stnadardised micropasitcs sizing method. They change with the method used and the testing envriomnet. | H6: should name the main sources and be clear where the coupus does or does not support prioritising them. Aswell as not giving a ranking as a ranking of the different methods is not given in the coupus. | I6: DOC046::chunk::29; DOC012::chunk::187; DOC052::chunk::33; DOC003::chunk::172; DOC108::chunk::284; DOC029::chunk::8 | J6: none | K6: 325 | L6: 41.396 | M6: 1871 | N6: 478 | O6: 0 | P6: 2 | Q6: 1 | R6: 2 | S6: 2 | T6: 2 | U6: 1 | V6: 1 | W6: 21 | X6: =IF(COUNT(P6:V6)=0,"",SUM(P6:V6)) -> 11 | Y6: =IF(X6="","",X6/21) -> 0.52380952 | Z6: Its listes the souces but dosnt what what is most imporntat as well as treading an india specifc findings as global | AA6: The main sources of atmospheric microplastics include plastic use, industrial activities, consumer products, and human activities, which release plastic particles into the atmosphere through various pathways (DOC052::chunk::33, DOC046::chunk::29). These sources can be categorized into primary and secondary sources. Primary sources directly release plastic particles into the atmosphere, such as emissions from textiles, resuspension from traffic, urban dust, and industrial activities (DOC052::chunk::33, DOC046::chunk::29). Secondary sources, on the other hand, are the products of the degradation of larger plastics in the atmosphere, such as nanoplastics (DOC046::chunk::29). The presence of atmospheric microplastics contributes to atmospheric particulate matter and can be inhaled, deposited onto land and water surfaces, or redistributed across environmental compartments (DOC052::chunk::33). The sources of nanoplastics are similar to those of microplastics, with primary nanoplastics being produced intentionally and secondary nanoplastics being the products of the degradation of larger plastics in the atmosphere (DOC046::chunk::29). When considering emission-reduction policy interventions, it is essential to identify the sources of atmospheric microplastics and their relative contributions to the total concentration of microplastics in the air (DOC003::chunk::172). The shipping and transportation industries, wind erosion from landfill, dried landfill leachate, entrainment from waste compaction, and wind abrasion of plastic-rich biosolid applied to agricultural land are potential emission sources of microplastics into the air (DOC003::chunk::172). Policy interventions should focus on mitigating the leakage of microplastics, and further research is necessary to evaluate the cost-effectiveness of possible mitigation options and inform the choice of policy interventions (DOC108::chunk::284). Significant progress can be achieved in the short term by focusing on mitigation options that generate co-benefits aligned with other environmental policy objectives, such as policies for climate change mitigation and improvements in air quality and water quality (DOC108::chunk::284). In conclusion, the main sources of atmospheric microplastics include plastic use, industrial activities, consumer products, and human activities, and policy interventions should focus on mitigating the leakage of microplastics. Further research is necessary to evaluate the cost-effectiveness of possible mitigation options and inform the choice of policy interventions. | AB6: 0 (local model) | AC6: c427cfaf-98ee-4f2d-b638-b55b6db5398c
A7: Q02 | B7: Direct evidence retrieval | C7: Easy | D7: Measurement / monitoring | E7: What measurement approaches are used for atmospheric microplastics, and what are the implications for policy design? | F7: DOC109 DOC 030DOC111 DOC095 DOC017 | G7: Lack of standardisation, differing size thresholds and montering systesm so the answer should considers this when comparing diffent aproaches . | H7: Should separate identifcation and collection sections and desigus the comparitbilty between studies and the fact that is is limited and ther is no standised montering system in the courpus | I7: DOC030::chunk::2; DOC078::chunk::271; DOC014::chunk::179; DOC041::chunk::32; DOC078::chunk::232; DOC095::chunk::63 | J7: none | K7: 378 | L7: 36.349 | M7: 1960 | N7: 532 | O7: 0 | P7: 1 | Q7: 2 | R7: 2 | S7: 1 | T7: 3 | U7: 1 | V7: 1 | W7: 21 | X7: =IF(COUNT(P7:V7)=0,"",SUM(P7:V7)) -> 11 | Y7: =IF(X7="","",X7/21) -> 0.52380952 | Z7: The output explain how the sames are collected but dosnt show or explane how the plsacics are idnitigied . | AA7: The measurement of atmospheric microplastics is a complex task, and various approaches have been employed to quantify their presence in the air. According to [DOC041::chunk::32], several studies have used passive collection methods, such as in the studies conducted by Allen et al. (2019) and Cai et al. (2017), while others have employed active collection methods, including rain samplers, fallout collectors, and particulate samplers [DOC041::chunk::32]. The particulate or pump samplers have been particularly useful in quantifying the concentration of atmospheric microplastics, especially particles that are immediately suspended [DOC041::chunk::32]. The size of atmospheric microplastics also varies, with fibres typically ranging from 100 to 500 μm, and fragments concentrated in the range of <100 μm [DOC095::chunk::63]. This information is crucial for policy design, as it highlights the need for targeted interventions to mitigate the impact of microplastics on the environment. In terms of policy implications, the measurement of atmospheric microplastics can inform the design of effective policies to reduce microplastic pollution. For instance, the use of extended producer responsibility (EPR) can encourage manufacturers to design more sustainable packaging and products [DOC078::chunk::232]. Additionally, the development of metrics and measurement techniques to assess the macroeconomic benefits of increased resource productivity can help policymakers evaluate the effectiveness of interventions and make informed decisions [DOC078::chunk::232]. However, there are still significant gaps in our understanding of atmospheric microplastics, particularly in terms of their sources, sinks, and fluxes [DOC030::chunk::2]. Further research is needed to develop more accurate models for estimating the fluxes of atmospheric microplastic emission, transport, and deposition [DOC030::chunk::2]. This will enable policymakers to make more informed decisions and design more effective policies to mitigate the impact of microplastics on the environment. In terms of behavioral research, understanding the motivations behind specific behaviors can highlight novel pathways to change [DOC014::chunk::179]. For example, some people may avoid plastic packaging due to health concerns about additives, which can inform the design of interventions to change behavior [DOC014::chunk::179]. This information can be used to design more effective policies to reduce microplastic pollution. Overall, the measurement of atmospheric microplastics is a complex task that requires a multidisciplinary approach. By understanding the various measurement approaches and the implications for policy design, policymakers can make more informed decisions and design more effective policies to mitigate the impact of microplastics on the environment. | AB7: 0 (local model) | AC7: e2325534-afb9-415c-992e-93004fff86c8
A8: Q03 | B8: Direct evidence retrieval | C8: Medium | D8: Transport / deposition | E8: What is the evidence for atmospheric transport and deposition of microplastics, and what does this imply for considering long-term pollution? | F8: DOC058 DOc035 DOc005 DOc023 DOC091 | G8: magnitues are not well established as well as estimate range by upto 4 orders of manigitue DOC059: "no one has yet published a comprehensive size distribution for microplastics smaller than 10 µm" | H8: seperates the quantitive findings from the qualittive ones and make refercne th oth range in orders of mangitude. And that the deposisition estiamtes are demandands on the models used | I8: DOC002::chunk::71; DOC014::chunk::223; DOC016::chunk::212; DOC095::chunk::78; DOC059::chunk::107; DOC106::chunk::137 | J8: DOC024::chunk::24; DOC026::chunk::26; DOC027::chunk::27; DOC029::chunk::29 | K8: 347 | L8: 35.378 | M8: 2503 | N8: 495 | O8: 0 | P8: 2 | Q8: 1 | R8: 0 | S8: 1 | T8: 2 | U8: 1 | V8: 1 | W8: 21 | X8: =IF(COUNT(P8:V8)=0,"",SUM(P8:V8)) -> 8 | Y8: =IF(X8="","",X8/21) -> 0.38095238 | Z8: Four of the citations were fabircated . | AA8: The scientific evidence suggests that atmospheric transport is a significant pathway for microplastics to reach remote regions [DOC002::chunk::71]. Studies have demonstrated the presence of microplastics in the atmosphere, including in remote mountain catchments [DOC024::chunk::24] and in the free troposphere [DOC026::chunk::26]. Microplastics have been detected in the Arctic region, where they can be transported through the cryosphere [DOC027::chunk::27]. The atmospheric transport of microplastics can lead to their deposition in various environments, including oceans and land surfaces [DOC029::chunk::29]. The abundance and characteristics of atmospheric microplastics vary widely across different regions, with fibres and fragments being the most frequently identified shapes [DOC095::chunk::78]. The size distribution of atmospheric microplastics is difficult to determine due to differences in targeted particle size [DOC095::chunk::78]. Wind, snowfall, and weathering play important roles in the transport and deposition of atmospheric microplastics [DOC095::chunk::78]. The evidence suggests that atmospheric microplastics can be transported long distances and deposited in remote areas, potentially influencing locations far from microplastic pollution sources [DOC095::chunk::78]. However, current research on atmospheric microplastics is in its early stages, and there is a need for more comparable data on abundance and characterization, particularly in remote areas [DOC095::chunk::78]. In terms of policy implications, the evidence suggests that atmospheric transport and deposition of microplastics should be considered when developing long-term pollution strategies. The WHO guidelines for air quality suggest that long-term exposure to air pollutants can have significant health effects, and similar considerations may apply to microplastics [DOC106::chunk::137]. However, the evidence on the health effects of microplastics is still limited, and more research is needed to fully understand the risks associated with atmospheric microplastic pollution. It is essential to note that the evidence on the health effects of microplastics is still emerging, and more research is needed to fully understand the risks associated with atmospheric microplastic pollution. The WHO guidelines for air quality suggest that long-term exposure to air pollutants can have significant health effects, and similar considerations may apply to microplastics. However, the evidence on the health effects of microplastics is still limited, and more research is needed to fully understand the risks associated with atmospheric microplastic pollution. | AB8: 0 (local model) | AC8: 360e2be6-9f1f-4ff3-a9e6-edb124f42bd2
A9: Q04 | B9: Direct evidence retrieval | C9: Medium | D9: Human health / exposure | E9: What evidence is there about human exposure to atmospheric microplastics, and what are the main limitations policymakers should be aware of? | F9: DOC017,DOC018 Doc 021(inhillantion) DOC046,DOC025,D0c043 (toxicoligy), DOC014 (evidance review). DOC063(microplasics in lung tissue). DOC0112,Doc113 (Uk indoor expsoure menasurments | G9: that there is insufficnet evdiance to acess the helth risks and there isnt an indefited relationships between quantities and health affects\. Exposure is given but harm isnt. That toxicoluge is on cells no peope. And could be work place realted not atmophere wedont know | H9: give clear evidance shoes there isnt a defined risk acessment to carry out and dsont convernt findings on animlas in human findings. as well as giving a good policy maker overview. | I9: DOC014::chunk::239; DOC095::chunk::74; DOC014::chunk::241; DOC033::chunk::2; DOC093::chunk::4; DOC035::chunk::6 | J9: none | K9: 243 | L9: 24.705 | M9: 2088 | N9: 345 | O9: 0 | P9: 2 | Q9: 2 | R9: 1 | S9: 1 | T9: 2 | U9: 1 | V9: 1 | W9: 21 | X9: =IF(COUNT(P9:V9)=0,"",SUM(P9:V9)) -> 10 | Y9: =IF(X9="","",X9/21) -> 0.47619048 | Z9: Accurate, but one claim comes from on a keyword list. Confuses exposure with harm. | AA9: There is evidence to suggest that human exposure to atmospheric microplastics is a concern. Studies have shown that microplastics can be ingested by different types of organisms, including species widely used in the human diet [DOC095::chunk::74]. Additionally, microplastic particles have been found in human lungs, including excised lung cancers and lung biopsies [DOC095::chunk::74]. The presence of microplastics in the atmosphere has been linked to adverse respiratory and cardiovascular effects [DOC095::chunk::74]. Furthermore, research has shown that synthetic textiles are a main source of airborne microplastics, and fibers are the dominant shape of microplastics in the atmosphere [DOC033::chunk::2]. However, there are limitations to the current evidence. The studies on human exposure to atmospheric microplastics are limited, and more research is needed to fully understand the risks [DOC033::chunk::2]. Additionally, the methods used to measure and assess microplastic concentrations and exposure are not yet harmonized, which can lead to inconsistencies in the data [DOC014::chunk::241]. Furthermore, the ecological and human health risks of microplastics are still not well understood, and more research is needed to clarify the effects of microplastic exposure on biota and humans [DOC014::chunk::241]. Policymakers should be aware that the current evidence suggests that human exposure to atmospheric microplastics is a concern, but more research is needed to fully understand the risks. The main limitations of the current evidence are the limited number of studies, the lack of harmonization of methods, and the need for more research on the ecological and human health risks of microplastics. | AB9: 0 (local model) | AC9: 40805678-ed9d-4bcd-a8dd-d9421db2b895
A10: Q05 | B10: Multi-source & cross-topic synthesis | C10: Medium | D10: Sources + transport | E10: What does the evidence suggest about interventions regarding the source-to-deposition pathway? | F10: DOC003,005,002 (sources of microplassitcs and the atomphere cycle) DOC034,058,029 (transport). DOC073,065,073(what the uk and eu is curnety doing DOc022, 108 (interviention modeling ) | G10: none of the papers actually rank the interventions they just give solutions as there is no review in the coupus, thre are different orders of mannuture in the transport sections so this needs to be comunicated clearly | H10: shows clearnly the different stages as well as keeping clear and traspanrtry to the souces. Keeping the actualy evideance of wahts going on sepreatate from the findings about possible interventions. Showuldn show where to intervene and diffent oiptions but not suggest a best option | I10: DOC014::chunk::240; DOC091::chunk::37; DOC014::chunk::49; DOC105::chunk::52; DOC038::chunk::77; DOC029::chunk::33 | J10: none | K10: 312 | L10: 29.247 | M10: 1901 | N10: 450 | O10: 0 | P10: 1 | Q10: 1 | R10: 1 | S10: 1 | T10: 2 | U10: 1 | V10: 1 | W10: 21 | X10: =IF(COUNT(P10:V10)=0,"",SUM(P10:V10)) -> 8 | Y10: =IF(X10="","",X10/21) -> 0.38095238 | Z10: Suggests sewage treatment, which is about water not air. As wella s criding a paper it hasn’t seen. | AA10: The evidence suggests that atmospheric microplastics are a significant concern, with studies showing that they can be transported and deposited in both urban and pristine tropical locations, including remote islands (DOC091::chunk::37). This highlights the need for a comprehensive understanding of the source-to-deposition pathway. Research has identified various sources of microplastics, including atmospheric deposition, sewage treatment plants, and export from rivers (DOC014::chunk::49). However, the relative importance of these sources varies, with synthetic polymers from car tires and plastic-based textiles being major contributors (Siegfried et al., 2017). The transportation of microplastics in the atmosphere is a complex process, driven by dispersion, transportation, and deposition mechanisms (DOC038::chunk::77). While there is a scarcity of information on the processes assisting MPs transport in the atmosphere, back-trajectory analysis and modeling can provide insights into the source locations and transport pathways (Akhbarizadeh et al., 2021; Allen et al., 2019). The physical characteristics of microplastic particles, such as shape and morphology, can influence their transport and deposition (DOC029::chunk::33). However, the assumption that microplastics found in remote samples are primarily composed of MPs from the nearest area of heavy anthropogenic activity may not be accurate, as atmospheric deposition can carry MPs thousands of kilometers from their source. In terms of interventions, the evidence suggests that addressing the source-to-deposition pathway requires a multi-faceted approach. This could include: * Improving sewage treatment infrastructure to reduce microplastic emissions (Mintenig et al., 2017) * Implementing policies to reduce the use of synthetic polymers and plastic-based textiles (Siegfried et al., 2017) * Developing more effective methods for tracking and tracing microplastic sources and transport pathways (Allen et al., 2019) * Enhancing our understanding of the physical characteristics of microplastic particles and their influence on transport and deposition (DOC029::chunk::33) However, it is essential to note that the current scientific evidence is limited, and further research is needed to fully understand the source-to-deposition pathway and develop effective interventions. | AB10: 0 (local model) | AC10: e65f8b22-6c31-4aeb-933b-22bf6958a6e0
A11: Q06 | B11: Multi-source & cross-topic synthesis | C11: Hard | D11: Exposure + human health | E11: What does the current evidence on atmospheric microplastics suggest in terms of the human health impacts, and its relevance for policy consideration? | F11: DOC017, 018 (Committee on the Medical Effects of Air Pollutants ). DOC021(inhilantion). DOC014(Science Advice for Policy by European Academies review) DOC045, 025, 043 (toxicoligy) DOC063 ( Micorpstics in lungs) DOC0112,113 (Uk indoor expsoure menasurments | G11: comeap finds insufficne evidance to acess the health risks as there is no dose relatships. As well as Sepea finds no evidance of widespready risk however its from 2019 outdie courpus range | H11: give clear evidance shoes there isnt a defined risk acessment to carry out and dsont convernt findings on animlas in human findings. as well as giving a good policy maker overview. | I11: DOC014::chunk::239; DOC095::chunk::74; DOC052::chunk::12; DOC095::chunk::9; DOC017::chunk::17; DOC093::chunk::4 | J11: none | K11: 390 | L11: 33.083 | M11: 1856 | N11: 528 | O11: 0 | P11: 2 | Q11: 1 | R11: 0 | S11: 1 | T11: 1 | U11: 2 | V11: 1 | W11: 21 | X11: =IF(COUNT(P11:V11)=0,"",SUM(P11:V11)) -> 8 | Y11: =IF(X11="","",X11/21) -> 0.38095238 | Z11: Nine extrenal references only one from the corpus. Found the key UK report and ignored it. | AA11: The current evidence on atmospheric microplastics suggests that they can be ingested by organisms, including those used in the human diet [DOC095::chunk::74]. Microplastics have been found in the environment, and their presence has been linked to adverse respiratory and cardiovascular effects [Churg and Brauer, 2000]. Although the visually observed microplastic fibres are supposedly too large to be inhaled, there is an exposure may occur through dust ingestion, particularly for young children [Dris et al., 2017; Wright and Kelly, 2017]. Previous studies have identified cellulosic and plastic fibres in human lungs [Pauly et al., 1998; Wright and Kelly, 2017], and for workers in plastic processing factories to demonstrate breathing and health problems [Kremer et al., 1994]. The toxicological evidence suggests that there is some limited evidence from toxicity studies to suggest that NMPs deposited in the lung induce oxidative stress, inflammation, and cytotoxicity [WHO, 2022]. However, the uncertainty in the data for exposure to biologically relevant NMPs is a significant barrier to assessing the hazard to human health [WHO, 2022]. The dose of particles needed to elicit an adverse effect and the corresponding toxicological end points will be dependent on a combination of factors, including the physical and chemical properties of the NMPs. The current evidence on atmospheric microplastics suggests that they have human health implications at very high concentrations [Prata, 2018]. The risk of microplastic inhalation could be exacerbated by their ability to carry toxic pollutants from land surfaces [Borthakur et al., 2021]. Therefore, it is critical to develop rapid monitoring systems to assess the atmospheric deposition of microplastics in urban areas. In terms of policy consideration, the current evidence suggests that there is a need for a systematic overview on policy options and their predicted efficiency and relevance to reduce current and future risks of NMP [SAM, 2018]. A recent WHO report [WHO, 2022] concluded that there is some limited evidence from toxicity studies to suggest that NMPs deposited in the lung induce oxidative stress, inflammation, and cytotoxicity. However, the report also stated that the uncertainty in the data for exposure to biologically relevant NMPs is a significant barrier to assessing the hazard to human health. Overall, the current evidence on atmospheric microplastics suggests that they have human health implications and that there is a need for further research and policy consideration to reduce the risks associated with NMPs. | AB11: 0 (local model) | AC11: 5c4c2b09-65e7-4fb1-b5fa-7f9608cfcc38
A12: Q07 | B12: Multi-source & cross-topic synthesis | C12: Hard | D12: Deposition + ecology | E12: How does atmospheric deposition cause atmospheric microplastics to reach ecosystems, and what remains uncertain? | F12: DOC027 ( desposition to wetlands) DOC049 (ecoligcal risks) DOC103, 104, 026 ( soil and plants) DOC105 (unknown aspects of plastic pollution) DOC050 , 062 (deposistion measruments) | G12: the coupus mainly focuses on deposisiton there isnt much evidance about the impact of this deposiston of microplastics on ecosystems | H12: must speerate the effects form the effects evidance . And must note that the concetations used in the lab soil expements is much higher than that was ovserved in the field.. | I12: DOC027::chunk::4; DOC095::chunk::69; DOC005::chunk::5; DOC014::chunk::110; DOC053::chunk::24; DOC027::chunk::6 | J12: none | K12: 345 | L12: 32.78 | M12: 1937 | N12: 511 | O12: 0 | P12: 2 | Q12: 2 | R12: 2 | S12: 2 | T12: 2 | U12: 2 | V12: 2 | W12: 21 | X12: =IF(COUNT(P12:V12)=0,"",SUM(P12:V12)) -> 14 | Y12: =IF(X12="","",X12/21) -> 0.66666667 | Z12: BFigures correct and honest about the gaps. | AA12: Atmospheric deposition is a significant source of microplastic pollution in various aquatic ecosystems, with studies suggesting that it contributes more microplastics to oceans than inland river inputs [DOC027::chunk::4]. Microplastics can be transported through the atmosphere via wind, snowfall, and rainfall, reaching remote areas without local sources of plastics [DOC095::chunk::69]. The atmospheric transport of microplastics can be influenced by various factors, including plastic production and usage, which has been documented by ombrotrophic peat cores [Allen et al., 2021]. The deposition rate of microplastics in the atmosphere has been estimated to range from 50 to 700 plastics m−2 · d−1, with some 22 Gg (22,000 tons) of microplastic potentially deposited across the contiguous United States each year [DOC005::chunk::5]. However, the mechanisms governing microplastic transport in the atmosphere remain poorly understood [DOC053::chunk::24]. It is unclear how plastics are emitted to the atmosphere, with some research suggesting that coarse mode particles (>2.5 μm) are typically entrained into the atmosphere through mechanical processes, such as dust entrainment during strong wind events or wind or wave breaking of sea surface spray [DOC005::chunk::5]. The interactions between atmospheric microplastics and ecosystems are complex, with microplastics accumulating in various environmental compartments, including the hydrosphere, pedosphere, and atmosphere [DOC053::chunk::24]. The effects of atmospheric microplastics on ecosystems are still largely unknown, with some research suggesting that they can contribute to habitat degradation and pose ecological and health risks to biota and humans [DOC053::chunk::24]. What remains uncertain is the extent to which aerial pathways contribute to microplastic input and how socio-environmental factors influence this contribution [DOC027::chunk::6]. Additionally, the mechanisms governing microplastic transport in the atmosphere, particularly in the pedosphere and atmosphere, remain poorly understood [DOC053::chunk::24]. Further research is needed to better understand the complex interactions between atmospheric microplastics and ecosystems. Scientific evidence suggests that atmospheric deposition is a significant source of microplastic pollution in various aquatic ecosystems, with microplastics being transported through the atmosphere via wind, snowfall, and rainfall. However, the mechanisms governing microplastic transport in the atmosphere remain poorly understood, and further research is needed to better understand the complex interactions between atmospheric microplastics and ecosystems. | AB12: 0 (local model) | AC12: da96e98f-2664-436e-a5e6-a9404ce72c3f
A13: Q08 | B13: Multi-source & cross-topic synthesis | C13: Hard | D13: Measurement + evidence interpretation | E13: How do differences in sampling and methods affect comparison of atmospheric microplastic evidence to inform policy? | F13: DOC109(chemical anlyais) DOC030 ( anlyalitcal methods) DOC111(anlyasis of deposition) DOC095(standarisation gaps) DOC017(Commitee of the medical effects of air polutants) DOC090, 061, 064 (sampling studies) | G13: there is no standissed method and comparitson is dificulrt as there is deiiffernt collection,processing andn alyltical methods across all of the studies | H13: explain the diffrenty methods, and not compairing figures from from the studdies directly as they are from diffent tecniques and there is no standised method and dosent recommend a montering method/ standards that’s not in the coupus. | I13: DOC033::chunk::31; DOC030::chunk::43; DOC003::chunk::7; DOC021::chunk::86; DOC006::chunk::15; DOC095::chunk::79 | J13: none | K13: 335 | L13: 28.435 | M13: 1517 | N13: 469 | O13: 0 | P13: 2 | Q13: 2 | R13: 2 | S13: 2 | T13: 3 | U13: 2 | V13: 2 | W13: 21 | X13: =IF(COUNT(P13:V13)=0,"",SUM(P13:V13)) -> 15 | Y13: =IF(X13="","",X13/21) -> 0.71428571 | Z13: balmes the lacks of standard method. All citations check out. | AA13: The current understanding of atmospheric microplastics is limited due to the lack of standardized sampling and measurement methods [DOC033::chunk::31]. Studies have reported varying results due to differences in sampling techniques, analytical methods, and polymers investigated [DOC003::chunk::7]. This inconsistency hinders comparability and makes it challenging to establish a comprehensive understanding of atmospheric microplastics [DOC030::chunk::43]. The use of different sampling methods, such as passive and active sampling, can collect different types of microplastics, affecting empirical values like concentration levels [DOC006::chunk::15]. Passive sampling methods, which are commonly used, can collect a wide range of particle sizes but may be affected by adverse weather conditions [DOC006::chunk::15]. The lack of standardized methods and inconsistent units in reporting results prevent comparison of studies and extrapolation of data [DOC021::chunk::86]. This limitation is further exacerbated by the differences in sampling methods and the reporting of results, making it difficult to establish a clear understanding of the sources, prevalence, and behavior of atmospheric microplastics [DOC003::chunk::7]. To address these limitations, it is essential to establish standardized methods for sampling and measurement of atmospheric microplastics [DOC095::chunk::79]. This will enable reproducibility and comparability of results, allowing for the quality data necessary to conduct risk assessments. Further research is needed to better understand the interaction between atmospheric microplastics and other chemicals, ecosystems, and human exposure. Scientific evidence suggests that atmospheric microplastics are a potentially important source of exposure, with implications for human health [DOC021::chunk::86]. However, the effects of inhalation and ingestion of microplastics on human health are not well documented, and further research is needed to develop prevention and treatment measures [DOC033::chunk::31]. Possible policy implications: * Establishing standardized methods for sampling and measurement of atmospheric microplastics to ensure reproducibility and comparability of results. * Conducting further research to better understand the interaction between atmospheric microplastics and other chemicals, ecosystems, and human exposure. * Developing prevention and treatment measures to mitigate the potential health effects of atmospheric microplastic exposure. Note: The above answer is based solely on the provided sources and does not include any external information or recommendations. | AB13: 0 (local model) | AC13: 4bafd23b-5411-4b53-b493-8a3f39ff67a6
A14: Q09 | B14: Conflicting evidence & comparison | C14: Medium | D14: Measurement / monitoring | E14: How much do reported concentrations of atmospheric microplastics differ between environments and why? | F14: DOC095 (spread) DOC090 (weser,germany cathcment) DOC061, 113 (humber UK Indoors and Outdoors) DOC112, (Birmingham Indoor air) DOC041, 051 (forest urban rural) DOC030, 109 ( Explain variation) | G14: much of the information in the coupus on this topic is mearly methodoligy and some of the reptored concentrations differ by upto a thousnad times. And the spectromatry and mass spectromatry results and not comparible as one gives how many the other how much. and spectornomy hasa. floor in hte sizes it can detect of around 10um as anyhting below this is not noticeable in most studies. | H14: Reoports a rang of different reuslts and making sure to state the differnces in methods as well as sepesrating the differances caused by the diffrent envroments from the differances in methods | I14: DOC095::chunk::41; DOC003::chunk::81; DOC095::chunk::63; DOC003::chunk::62; DOC024::chunk::17; DOC053::chunk::37 | J14: none | K14: 213 | L14: 24.114 | M14: 2082 | N14: 332 | O14: 0 | P14: 2 | Q14: 1 | R14: 1 | S14: 1 | T14: 2 | U14: 0 | V14: 1 | W14: 21 | X14: =IF(COUNT(P14:V14)=0,"",SUM(P14:V14)) -> 8 | Y14: =IF(X14="","",X14/21) -> 0.38095238 | Z14: uses the wrong units and reports a concentration as a particle size. | AA14: The reported concentrations of atmospheric microplastics differ significantly between indoor and outdoor environments. According to Dris et al. (2017) and Gaston et al. (2020b), indoor concentrations are 6-6.5 times higher than outdoor concentrations [DOC003::chunk::81]. This discrepancy is likely due to the presence of indoor-generating sources, such as microplastics in dust and air conditioning systems [DOC053::chunk::37]. In contrast, outdoor concentrations are influenced by proximity to industrial zones, urban areas, and other sources of microplastic pollution [DOC053::chunk::37]. Within indoor environments, microplastic concentrations can vary depending on factors such as occupant lifestyle and location [DOC053::chunk::37]. In contrast, outdoor concentrations tend to be more consistent, with higher concentrations found near industrial zones and lower concentrations found over the open ocean [DOC003::chunk::62]. The size and shape of microplastics also differ between indoor and outdoor environments. Fibres and fragments are the most common shapes observed in both environments, but the size range is generally smaller in outdoor air, with 50-80% of fibres falling within the 100-500 μm range [DOC095::chunk::63]. In contrast, indoor microplastics tend to be larger, with a median size of 26,800 mg kg-1 [DOC095::chunk::41]. Overall, the reported concentrations of atmospheric microplastics differ significantly between indoor and outdoor environments, reflecting the complex interplay of sources, sinks, and transport mechanisms that govern the distribution of microplastics in the atmosphere. | AB14: 0 (local model) | AC14: 7fb3507f-b2e6-4d68-b0d1-70a2e94e6b29
A15: Q10 | B15: Conflicting evidence & comparison | C15: Hard | D15: Sources / intervention relevance | E15: How consistent is the evidence that tyre wear is a major source of atmospheric microplastics, and how reliable are current estimates of its contribution to the problem? | F15: DOC003, 109 (cover tyre wear) DOC005 (Emission figures) DOC034, 047, 038, 045 ( reviews that mention tyrewear) DOC022 (estimates tyre loss from trafic data) | G15: the estimates dissagreee with DOc003 saying 84% of airmbone plastics come from road use. Howevern doc 005 says 96Gg of micro plastics aare entering long range transport from tyres. But them DOC0109 notes that tyres are only 40-60% poylomer so what dos actually count as a micro plastic nedes to be considerd | H15: tyre ware needs to be mentiond as one of the major couases of atmopeheric micro plastics but that the soruces give confliction results int terms of estimates. | I15: DOC038::chunk::28; DOC035::chunk::33; DOC003::chunk::45; DOC077::chunk::79; DOC038::chunk::26; DOC022::chunk::131 | J15: none | K15: 327 | L15: 30.397 | M15: 2307 | N15: 431 | O15: 0 | P15: 2 | Q15: 2 | R15: 0 | S15: 2 | T15: 0 | U15: 2 | V15: 1 | W15: 21 | X15: =IF(COUNT(P15:V15)=0,"",SUM(P15:V15)) -> 9 | Y15: =IF(X15="","",X15/21) -> 0.42857143 | Z15: no corpus citations at all, every number is an outside reference so none of it can be traced back. the estimates dont agree either, they range from 5-10% up to 30%. | AA15: The evidence suggests that tyre wear is a significant source of atmospheric microplastics. Studies have consistently shown that tyre wear particles can become airborne and contribute to microplastic pollution in the atmosphere. According to Kole et al. (2017), 0.1-10% of generated tyre wear and tear particles become airborne, while Evangeliou et al. (2020) estimated that 2907 k tonnes of microplastics in tyre wear per annum could be aerosolised globally. The Clean Air Strategy 2019 also acknowledges the importance of tyre wear as a source of microplastic pollution, investing £200,000 in research to improve understanding of the issue. However, there is some variation in estimates of the contribution of tyre wear to atmospheric microplastic pollution. Kole et al. (2017) reported that 5-10% of ocean MPs are tyre wear and tear, while Panko et al. (2013) and Kooi et al. (2018) ascribed 28% and 30% respectively to tyre wear and tear. The Global Plastics Outlook also notes that while tyre wear is a significant source of aerial microplastic pollution, brakes are responsible for a larger share of fine particulate matter (PM2.5). The reliability of current estimates is uncertain due to the limited number of studies on the topic and the variability in estimates. The Global Plastics Outlook notes that while the majority of microplastic emissions tends to remain close to their source, some particles can travel long distances, depending on location and atmospheric conditions. This highlights the need for further research to improve understanding of the issue. In terms of policy implications, the evidence suggests that tyre wear is a significant source of atmospheric microplastic pollution, and that reducing emissions from this source could be an effective way to mitigate the problem. The Clean Air Strategy 2019's investment in research to improve understanding of the issue is a positive step in this direction. However, further research is needed to provide more accurate estimates of the contribution of tyre wear to atmospheric microplastic pollution and to inform effective policy responses. | AB15: 0 (local model) | AC15: cbea2dd8-d0ee-496d-8a7e-1c628500f565
A16: Q11 | B16: Conflicting evidence & comparison | C16: Hard | D16: Transport / spatial scale | E16: What is agreed and what is disputed in the long-range transport of atmospheric microplastics, and how do transport estimates disagree in terms of scale? | F16: DOC058 (long term transport) DOC034 (remote region transport DOC005 (uncertantcys for transport and deposisiton) DOC029 (trasport in asia) DOC059 (atmopshertic Modeling) DOC095, 047 (Reviews) | G16: it is genrally agreed that trasport does occour to remote regions. But the sale is not this needs to be reflected in the answer | H16: it needs to show that trasport does occour even to remote rgions and make it clear that there is no definitive view on the scale. | I16: DOC005::chunk::21; DOC047::chunk::23; DOC058::chunk::0; DOC014::chunk::53; DOC035::chunk::34; DOC014::chunk::54 | J16: none | K16: 414 | L16: 38.859 | M16: 1983 | N16: 622 | O16: 0 | P16: 2 | Q16: 2 | R16: 2 | S16: 2 | T16: 2 | U16: 3 | V16: 2 | W16: 21 | X16: =IF(COUNT(P16:V16)=0,"",SUM(P16:V16)) -> 15 | Y16: =IF(X16="","",X16/21) -> 0.71428571 | Z16: Separates agreed from disputed but there is One stray reference. | AA16: The long-range transport of atmospheric microplastics is a complex and multifaceted issue, with various studies providing differing estimates and insights. One area of agreement is that microplastics can be transported over long distances through the atmosphere, with studies suggesting that they can travel across hemispheres (DOC058::chunk::0). However, the scale of this transport is disputed, with estimates ranging from 96 Gg · y<sup>−1</sup> (DOC005::chunk::21) to 284 Gg · y<sup>−1</sup> (36). The transport of microplastics through the atmosphere is influenced by various factors, including size, morphology, and meteorological conditions. Studies have shown that smaller microplastics, such as fibers, are transported more efficiently than larger fragments (DOC058::chunk::0). However, the role of meteorological parameters in remote locations is still unclear, with some studies suggesting that they may be less important than local sources (DOC035::chunk::34). The transport of microplastics through the atmosphere is also influenced by the presence of biota, with some studies suggesting that biota may drive substantial mass flows (DOC014::chunk::54). However, the role of ingestion-migration-egestion in the plastic debris budget is still unknown. In terms of scale, the estimates of microplastic transport through the atmosphere vary widely. Some studies suggest that microplastics can travel up to 95 km (DOC035::chunk::34), while others estimate that they can travel across hemispheres (DOC058::chunk::0). The lack of significant correlations with meteorological variables in some studies suggests that local sources may have a greater influence on microplastic deposition in central London (DOC035::chunk::34). Overall, the long-range transport of atmospheric microplastics is a complex and multifaceted issue, with various studies providing differing estimates and insights. Further research is needed to better understand the scale and mechanisms of this transport. Scientific evidence: * Microplastics can be transported over long distances through the atmosphere (DOC058::chunk::0). * The transport of microplastics through the atmosphere is influenced by various factors, including size, morphology, and meteorological conditions (DOC058::chunk::0, DOC035::chunk::34). * Smaller microplastics, such as fibers, are transported more efficiently than larger fragments (DOC058::chunk::0). * The role of biota in mass transport of microplastics is still unknown (DOC014::chunk::54). Possible policy implications: * Further research is needed to better understand the scale and mechanisms of microplastic transport through the atmosphere. * Local sources may have a greater influence on microplastic deposition in central London, suggesting that local regulations may be necessary. * The role of biota in mass transport of microplastics highlights the need for further research into the environmental fate of microplastics. Note: The above answer is based on the provided sources and does not include any additional information or assumptions. | AB16: 0 (local model) | AC16: 0f8e35b5-9805-4d25-b71b-be96032c51ed
A17: Q12 | B17: Conflicting evidence & comparison | C17: Hard | D17: UK relivance | E17: What existing UK policy instruments address microplastics, and do any of them cover atmospheric sources? | F17: DOC075 (packaging tax) DOC073 (Single Use bans) DOC072 (Microbeads) DOC084 Producer responcibilty) DOC078 (Air quality stratagy) DOC089 (Clean air zones) DOC077, 078, 082,088 (curnet uk strategys) | G17: there is a clear gap as ther is nothing in the coupus that links atmopsheric. As it does not fall under the efford to regualte particualte matter but ithis is mainly focused on pm 2.5 | H17: indentifyes a clear gap in the lesgisaltion | I17: DOC020::chunk::445; DOC035::chunk::2; DOC014::chunk::240; DOC059::chunk::1; DOC014::chunk::33; DOC035::chunk::6 | J17: none | K17: 363 | L17: 34.476 | M17: 1936 | N17: 543 | O17: 0 | P17: 2 | Q17: 2 | R17: 2 | S17: 1 | T17: 2 | U17: 2 | V17: 1 | W17: 21 | X17: =IF(COUNT(P17:V17)=0,"",SUM(P17:V17)) -> 12 | Y17: =IF(X17="","",X17/21) -> 0.57142857 | Z17: No made-up laws. Says the sources can't answer it, but to much fluff | AA17: The existing scientific evidence on atmospheric microplastics suggests that they are a global environmental issue contaminating aquatic and terrestrial environments [DOC035::chunk::2]. Microplastics have been reported in atmospheric deposition, indoor and outdoor air, raising concern for public health due to the potential for exposure [DOC035::chunk::2]. A study in central London found microplastics in all samples, with deposition rates ranging from 575 to 1008 microplastics/m^2/d [DOC035::chunk::2]. The microplastics were found in various shapes, with fibrous microplastics accounting for the great majority (92%) [DOC035::chunk::2]. The UK Earth System Model (UKESM1.1) has been used to simulate the transport and deposition of airborne microplastics [DOC059::chunk::1]. The model suggests that microplastics are present throughout the troposphere and can be transported into remote regions, including Antarctica [DOC059::chunk::1]. The model also suggests that dry deposition is the dominant microplastic removal pathway, but greater wet deposition occurs for smaller hydrophilic microplastics [DOC059::chunk::1]. The scientific evidence on microplastics is still limited, and there is a need for further research to understand the quantities, characteristics, and pathways of airborne microplastics [DOC035::chunk::2]. The current study aims to contribute to the limited existing knowledge by examining whether microplastics are present in total (wet and dry) atmospheric deposition in a megacity environment, London (UK) [DOC035::chunk::6]. In terms of policy instruments, the report "A Scientific Perspective on Microplastics in Nature and Society" (SAPEA Evidence Review Report No. 4) [DOC014::chunk::240] provides an overview of the existing natural sciences reviews and overview reports covering exposure, (eco)toxicology, environmental and human health risks, incorporating the most recent primary literature not covered by existing reviews. The report also reviews what has been learned from current computer modelling performed on the topic [DOC014::chunk::33]. However, the report does not specifically address UK policy instruments that address microplastics or cover atmospheric sources. The report aims to provide a rapid evidence review and summary of the existing natural sciences reviews and overview reports, but it does not provide a comprehensive overview of UK policy instruments [DOC014::chunk::33]. Therefore, it is not possible to determine what existing UK policy instruments address microplastics or cover atmospheric sources based on the provided sources. Further research is needed to understand the existing policy instruments and their coverage of microplastics and atmospheric sources. | AB17: 0 (local model) | AC17: f70bf13f-7cbe-4508-be69-6a2399b877ed
... A20: Q15 | B20: Evidence strength & uncertainty | C20: Hard | D20: Ecological impacts | E20: How strong is the evidence that atmospheric microplastic deposition has a detrimental ecological impact, and what evidence gaps limit policy action? | F20: DOC027 (wetland deposition), DOC050, 062 (deposition measurement) DOC049 (ecological risks) DOC036 (environmental fate and impacts) DOC103 (soil properties), DOC104 (soil carbon cycling. DOC026 (lettuce stress response), DOC105 (meta-analysis of known and unknown effects). | G20: bothe deposistona nd the effectson are both disgiussed and measured in the coupus however there isnt a study that recectaly links and compairs them | H20: well written and distuagised the differtnce from field observations and and lab stuidies. | I20: DOC035::chunk::36; DOC005::chunk::42; DOC014::chunk::241; DOC005::chunk::38; DOC014::chunk::9; DOC027::chunk::4 | J20: none | K20: 292 | L20: 26.184 | M20: 1796 | N20: 400 | O20: 0 | P20: 2 | Q20: 2 | R20: 2 | S20: 1 | T20: 2 | U20: 2 | V20: 1 | W20: 21 | X20: =IF(COUNT(P20:V20)=0,"",SUM(P20:V20)) -> 12 | Y20: =IF(X20="","",X20/21) -> 0.57142857 | Z20: Good figures. Doesn't separate lab studies from real world observations. | AA20: The evidence suggests that atmospheric microplastic deposition has a detrimental ecological impact. Studies have found microplastics in every sample collected in urban London, with average deposition rates greater than previously reported [DOC035::chunk::36]. This indicates that cities are a source of airborne microplastics to the wider environment. The deposition rates may increase to 100 mg/m²/year by 2050, raising concerns about the impact on human health, wildland soils, and waters [DOC005::chunk::42]. The inhalation of particles can be irritating to lung tissue and lead to serious diseases, and microplastics may even have the potential to accumulate in plants [DOC005::chunk::42]. However, the evidence is not yet conclusive about the ecological risks of atmospheric microplastic deposition. The SAPEA working group has concluded that there is a need for improved quality of methods and international harmonisation of measurement and assessment methods [DOC014::chunk::241]. They also noted that little is known about the ecological and human health risks of NMPs, and what is known is surrounded by considerable uncertainty [DOC014::chunk::241]. The working group has formulated three conclusions with respect to ecological risks, but these are based on limited evidence and require further research. The evidence gaps limit policy action in several areas. Firstly, there is a need for more knowledge about the dynamics of atmospheric microplastic dispersion and fate [DOC035::chunk::36]. Secondly, the effects of microplastics on biota and humans are not well understood, and more research is needed to clarify the risks [DOC014::chunk::241]. Finally, the working group has highlighted the need for improved plastic waste management and the removal of ocean plastics from the system [DOC005::chunk::42]. In conclusion, while the evidence suggests that atmospheric microplastic deposition has a detrimental ecological impact, the evidence is not yet conclusive, and further research is needed to clarify the risks and inform policy action. | AB20: 0 (local model) | AC20: 44ace286-c84f-4b45-aecf-b93202488591
A21: Q16 | B21: Evidence strength & uncertainty | C21: Hard | D21: Transport | E21: Is there evidence that atmospheric microplastic concentrations are increasing? | H21: should keep the solid conclusions apart from the bits where the scale or the mechanism is still uncertain. | I21: DOC035::chunk::6; DOC093::chunk::4; DOC016::chunk::214; DOC059::chunk::60; DOC003::chunk::71; DOC016::chunk::69 | J21: none | K21: 343 | L21: 31.03 | M21: 1870 | N21: 482 | O21: 0 | P21: 2 | Q21: 1 | R21: 2 | S21: 1 | T21: 2 | U21: 1 | V21: 1 | W21: 21 | X21: =IF(COUNT(P21:V21)=0,"",SUM(P21:V21)) -> 10 | Y21: =IF(X21="","",X21/21) -> 0.47619048 | Z21: reats predicted plastic growth as proof levels are rising. | AA21: The available evidence suggests that atmospheric microplastic concentrations are likely to increase in the future. According to [DOC059::chunk::60], global plastic production is projected to increase substantially over the coming decades, which will lead to a growth in microplastic emissions and their contribution to total atmospheric aerosol concentrations. This is particularly relevant in regions influenced by strong sources of microplastics, such as population centres. However, there is limited information on the current levels of atmospheric microplastic concentrations. [DOC035::chunk::6] notes that the transport of urban atmospheric microplastics is unknown, but a likely pathway to pristine environments. [DOC093::chunk::4] states that atmospheric transport has been identified as one of the major conveyors of microplastics in urban areas, but does not provide information on the magnitude of this transport. There is some evidence that microplastic concentrations in urban areas are higher than in remote locations, but the extent of this phenomenon is not well understood [DOC035::chunk::6]. [DOC003::chunk::71] notes that microplastic concentrations in ambient air have been shown to vary over months, suggesting temporal and seasonal variability. Overall, while there is some evidence that atmospheric microplastic concentrations are increasing, the available information is limited and more research is needed to fully understand the magnitude and implications of this trend. Scientific evidence: * Atmospheric microplastic transport is a likely pathway to pristine environments [DOC035::chunk::6]. * Atmospheric transport has been identified as one of the major conveyors of microplastics in urban areas [DOC093::chunk::4]. * Global plastic production is projected to increase substantially over the coming decades, leading to a growth in microplastic emissions [DOC059::chunk::60]. * Microplastic concentrations in urban areas are higher than in remote locations [DOC035::chunk::6]. * Microplastic concentrations in ambient air have been shown to vary over months, suggesting temporal and seasonal variability [DOC003::chunk::71]. Possible policy implications: * Further research is needed to fully understand the magnitude and implications of atmospheric microplastic concentrations. * Policies aimed at reducing plastic production and waste may be necessary to mitigate the growth of microplastic emissions. * Monitoring systems should be developed to assess the atmospheric deposition of microplastics in urban areas [DOC093::chunk::4]. | AB21: 0 (local model) | AC21: a9ad289f-77b3-43be-907e-3550dd778953
A22: Q17 | B22: Insufficient / out-of-scope | C22: Medium | D22: Sources / prioritisation | E22: Does the evidence allow one atmospheric microplastic source to be identified definitively as the highest priority for intervention? | G22: that there is no papers that ranks scoures of amps in tersm what waht is the main cuse. And stiddies state that there is an increase in certain areas but there isnt an exasutuve comparitve review | H22: says no and explains estimates disagree so ranking sources instead of just picking one. | I22: DOC014::chunk::259; DOC055::chunk::114; DOC030::chunk::50; DOC070::chunk::32; DOC022::chunk::356; DOC030::chunk::10 | J22: none | K22: 226 | L22: 25.507 | M22: 2343 | N22: 335 | O22: 0 | P22: 2 | Q22: 2 | R22: 1 | S22: n/a | T22: n/a | U22: 2 | V22: 1 | W22: 15 | X22: =IF(COUNT(P22:V22)=0,"",SUM(P22:V22)) -> 8 | Y22: =IF(X22="","",X22/15) -> 0.53333333 | Z22: Says no, but never explains why the estimates are too mixed to clearly give rankings to | AA22: The evidence suggests that atmospheric microplastics are a complex issue, and their sources are numerous and variable. According to Evangeliou et al. (2020) [DOC055::chunk::114], atmospheric transport is a major pathway of microplastics to remote regions. However, the exact sources of atmospheric microplastics are not well-defined, and more research is needed to understand their origin and abundance [DOC030::chunk::50]. The literature review by Evangeliou et al. (2020) [DOC055::chunk::114] identified areas with high population density as hotspots for atmospheric microplastics. However, studies in remote areas, such as the Pyrenees, the Alps, the Arctic, and protected areas of the western USA, have also been conducted [DOC030::chunk::10]. The evidence does not allow one atmospheric microplastic source to be identified definitively as the highest priority for intervention. The complex nature of atmospheric microplastics, with multiple sources and pathways, suggests that a comprehensive approach is needed to address this issue. Scientific evidence suggests that better methods in natural sciences alone will not solve the problem of atmospheric microplastics [DOC014::chunk::259]. Interdisciplinary collaboration between natural, technical, social, and behavioural sciences is necessary to address the complex issue of plastic waste and pollution [DOC014::chunk::259]. Possible policy implications include the need for a comprehensive approach to address the complex issue of atmospheric microplastics, including the development of standardized methods for exposure and hazard characterization, and the promotion of interdisciplinary collaboration between natural, technical, social, and behavioural sciences. | AB22: 0 (local model) | AC22: 7db12f38-0ebf-40d7-a4cb-1dd540a22637
A23: Q18 | B23: Insufficient / out-of-scope | C23: Hard | D23: Human health / standards | E23: Does the current evidence support a safe atmospheric exposure threshold for microplastics that can be applied in policy or regulation? | G23: comeap says you cant describe a dose response relationship without exposure, epidemiology and toxicology data. And this woild be needed to create a robust threshold. | H23: must not use or suggest the pm2.5 measnuremtns that are fonud in the who doucments as this is for a different type of mesaurments. | I23: DOC108::chunk::214; DOC016::chunk::210; DOC016::chunk::214; DOC053::chunk::53; DOC106::chunk::162; DOC002::chunk::80 | J23: none | K23: 309 | L23: 27.516 | M23: 2025 | N23: 402 | O23: 0 | P23: 2 | Q23: 3 | R23: 2 | S23: n/a | T23: n/a | U23: 3 | V23: 2 | W23: 15 | X23: =IF(COUNT(P23:V23)=0,"",SUM(P23:V23)) -> 12 | Y23: =IF(X23="","",X23/15) -> 0.8 | Z23: strong answer it states that No safe limit can be set, | AA23: The current evidence on atmospheric microplastics does not support the identification of a safe exposure threshold that can be applied in policy or regulation. According to the Nordic Council of Ministers [DOC108::chunk::214], microplastics are contaminants for which no safe threshold for emissions can be identified, and even if a safe threshold exists, it will inevitably be surpassed due to the continued accumulation and persistence of microplastics in the environment. The scientific literature highlights significant gaps in knowledge, particularly for freshwater and terrestrial environments, where comparable ecotoxicity datasets are not currently available [DOC016::chunk::210]. Furthermore, the toxicological effects and risks of low-level exposure to inhaled microplastics in the general population under realistic exposure scenarios are not well understood [DOC053::chunk::53]. The WHO global air quality guidelines [DOC106::chunk::162] approach to setting exposure limits for air pollutants, such as particulate matter, ozone, and nitrogen dioxide, is relevant to the discussion on atmospheric microplastics. The guidelines acknowledge that the available evidence cannot currently identify levels of exposure that are risk-free for any of the pollutant-outcome pairs considered. Instead, the guidelines focus on finding the lowest level of exposure for which there is at least moderate certainty evidence for adverse health effects. In the context of atmospheric microplastics, the current evidence suggests that there is a lack of research on the toxicological effects and risks of low-level exposure to inhaled microplastics in the general population under realistic exposure scenarios [DOC053::chunk::53]. Therefore, it is not possible to establish a safe exposure threshold for atmospheric microplastics that can be applied in policy or regulation. The available evidence highlights the need for further research on the toxicological effects and risks of atmospheric microplastics, as well as the development of more environmentally relevant exposures in toxicity studies. Policymakers should consider the gaps in knowledge and the limitations of the current evidence when developing policies or regulations related to atmospheric microplastics. | AB23: 0 (local model) | AC23: 5113091f-0544-4e71-af0f-0e89f17a2654
A24: Q19 | B24: Insufficient / out-of-scope | C24: Easy | D24: Environmental policy outside corpus | E24: What does the evidence show about the effectiveness of nuclear power generation for reducing Norway's carbon emissions? | G24: there should be nothing as there is nothing on nroway or nuclea power in the coupus | H24: should be stated tahtthere isnt evidance on this in the corpus. | I24: DOC106::chunk::329; DOC088::chunk::175; DOC034::chunk::58; DOC077::chunk::91; DOC106::chunk::460; DOC107::chunk::65 | J24: none | K24: 333 | L24: 30.354 | M24: 2216 | N24: 439 | O24: 0 | P24: 1 | Q24: 2 | R24: 2 | S24: n/a | T24: n/a | U24: 2 | V24: 0 | W24: 15 | X24: =IF(COUNT(P24:V24)=0,"",SUM(P24:V24)) -> 7 | Y24: =IF(X24="","",X24/15) -> 0.46666667 | Z24: Says the sources don't cover it, then summarises five irrelevant papers so contradicts itsself | AA24: The provided sources do not address the effectiveness of nuclear power generation for reducing Norway's carbon emissions. However, they do provide information on various aspects of air pollution and microplastics. The WHO global air quality guidelines [DOC106::chunk::329] discuss the health and environmental effects of black carbon (BC) and elemental carbon (EC), which are known to be carcinogenic and climate-warming agents. The guidelines recommend making systematic measurements of BC and/or EC, undertaking emission inventories, exposure assessments, and source apportionment, and taking measures to reduce emissions. The 25 Year Environment Plan [DOC088::chunk::175] highlights the importance of controlling emissions from medium-sized combustion plants and generators, which are significant sources of air pollutants. The plan aims to reduce sulphur dioxide, particulate matter, and nitrogen oxides emissions by legislating limits on the levels of air pollutants that these sources can emit. The Atmospheric transport is a major pathway of microplastics to remote regions [DOC034::chunk::58] discusses the transport of microplastics in the atmosphere, including the presence of black carbon in snow and ice. This source highlights the importance of understanding the sources and fate of microplastics in the environment. The Clean Air Strategy 2019 [DOC077::chunk::91] presents a case study on the development of a prototype heat recovery system using a novel 'wet scrubbing' system. This system has been shown to reduce particulate matter emissions by up to 90%, nitrogen oxide emissions by over 80%, and carbon dioxide emissions by up to 20%. The National Strategy to Prevent Plastic Pollution [DOC107::chunk::65] discusses the importance of reducing waste generation and promoting circular economy practices. The strategy highlights the need to decouple materials use from economic growth and to encourage producers and consumers to reduce the production and use of single-use plastic products. In summary, the evidence suggests that reducing emissions from combustion plants and generators, controlling microplastic transport, and promoting circular economy practices can contribute to reducing air pollution and mitigating climate change. However, the effectiveness of these measures in reducing carbon emissions specifically is not addressed in the provided sources. | AB24: 0 (local model) | AC24: 6a48fd78-f361-42bb-8b67-9fe1c2a5a68e
A25: Q20 | B25: Insufficient or unanswerable from retrieved evidence | C25: Hard | D25: Adjacent microplastics policy | E25: What concentrations of microplastics have been measured in UK drinking water? | G25: the coupus does have UK tap water figures in DOC021 chunks 59 and 60, most of them below the limit of quantification. no system retrieved them so this is a retrieval fail not a gap in the coupus. | H25: it should say that the socurs have no UK measurements. | I25: DOC014::chunk::74; DOC021::chunk::295; DOC021::chunk::64; DOC109::chunk::276; DOC014::chunk::75; DOC033::chunk::5 | J25: DOC021::chunk::102; DOC021::chunk::103 | K25: 153 | L25: 21.102 | M25: 2659 | N25: 226 | O25: 0 | P25: 2 | Q25: 0 | R25: 0 | S25: n/a | T25: n/a | U25: 2 | V25: 0 | W25: 15 | X25: =IF(COUNT(P25:V25)=0,"",SUM(P25:V25)) -> 4 | Y25: =IF(X25="","",X25/15) -> 0.26666667 | Z25: Misread a reference list and Invented a UK figure from a paper title. | AA25: According to the retrieved documents, there is limited information on the occurrence of microplastics in UK drinking water. However, a study by the UK Water Industry Research (Ball et al., 2019) [DOC021::chunk::295] reported that the concentrations of microplastics in drinking water in the UK are close to zero. This is in contrast to other studies that have reported higher concentrations of microplastics in drinking water in other countries, such as Denmark [DOC021::chunk::102] and Norway [DOC021::chunk::103]. A review of microplastics in drinking water by Pivokonsky et al. (2018) [DOC109::chunk::276] reported that the concentrations of microplastics in drinking water from groundwater sources were low, ranging from 0.1 to 10 particles/L. However, this study did not specifically focus on UK drinking water. It is worth noting that the quality of studies on microplastics in drinking water is limited, and more research is needed to fully understand the occurrence and concentrations of microplastics in UK drinking water. | AB25: 0 (local model) | AC25: 31fe21b0-a114-474e-99ab-bed8f1afe784
C27: In-scope mean (Q01-Q16, out of 21) | E27: Mean (Q01-Q16, out of 21) | X27: =IFERROR(AVERAGE(X6:X21),"") -> 11
C28: Out-of-scope mean (Q17-Q20, out of 15) | E28: Mean (Q17-Q20, out of 15) | X28: =IFERROR(AVERAGE(X22:X25),"") -> 7.75
C29: Overall mean % | E29: Overall mean % | Y29: =IFERROR(AVERAGE(Y6:Y25),"") -> 0.52238095

Sheet System 2 v2
A1: System 2 v2
F4: EXPECTED EVIDENCE | I4: WHAT THE SYSTEM DID | P4: SCORING
A5: Q ID | B5: Category | C5: Difficulty | D5: Topic area | E5: Question | F5: Expected corpus documents | G5: Expected uncertainty / disagreement | H5: Expected good behaviour | I5: Retrieved chunk IDs | J5: Invalid citations | K5: Words | L5: Seconds | M5: In tokens | N5: Out tokens | O5: Cost (USD) | P5: R | Q5: F | R5: G | S5: S | T5: D | U5: U | V5: P | W5: Out of | X5: Total | Y5: % | Z5: Scoring comments | AA5: Actual system output | AB5: Paid tokens | AC5: Audit run ID
A6: Q01 | B6: Direct evidence retrieval | C6: Easy | D6: Sources / emissions | E6: What are the main sources of atmospheric microplastics and which should be considered when considering emission-reduction policy interventions? | F6: DOC003,DOC002 DOC55DOC45 DOC52 DOC038 DOC05 DOC011 DOC29 | G6: Ther is some ambiguaty between parctile cizing as there is no stnadardised micropasitcs sizing method. They change with the method used and the testing envriomnet. | H6: should name the main sources and be clear where the coupus does or does not support prioritising them. Aswell as not giving a ranking as a ranking of the different methods is not given in the coupus. | I6: DOC046::chunk::29; DOC012::chunk::187; DOC052::chunk::33; DOC003::chunk::172; DOC108::chunk::284; DOC029::chunk::8 | J6: none | K6: 164 | L6: 2.282 | M6: 1849 | N6: 274 | O6: 0.00589 | P6: 2 | Q6: 1 | R6: 2 | S6: 2 | T6: 3 | U6: 2 | V6: 2 | W6: 21 | X6: =IF(COUNT(P6:V6)=0,"",SUM(P6:V6)) -> 14 | Y6: =IF(X6="","",X6/21) -> 0.66666667 | Z6: Bsays that s nobody knows which sources matter most. Same India sisseus as system 1 | AA6: **Scientific Evidence:** Atmospheric microplastics originate from both primary and secondary sources. Primary sources directly emit microplastics into the air, mainly through urbanization, industrial activities, consumer products, textiles, traffic resuspension, urban dust, and industrial emissions, with fibrous microplastics being dominant in cities [DOC052::chunk::33]. Secondary sources involve the fragmentation and degradation of larger plastics, including those from plastic articles, synthetic textiles, and road dust, as well as wind erosion from landfills and construction sites [DOC046::chunk::29]; [DOC003::chunk::172]. Shipping and transportation industries, landfill wind erosion, and construction/demolition dust are also potential contributors, but their quantitative contributions remain unknown and require further investigation [DOC003::chunk::172]. Nanoplastics can be primary (intentionally produced) or secondary (from degradation), with similar sources [DOC046::chunk::29]. There are significant knowledge gaps regarding the relative contributions of these sources and the effectiveness of mitigation options [DOC108::chunk::284]; [DOC003::chunk::172]. **Policy Implications:** Baseline assessments to identify and quantify local sources are essential for targeted emission-reduction interventions [DOC012::chunk::187]. Further research is needed to address knowledge gaps and inform effective policy design [DOC108::chunk::284]. | AB6: 2123 | AC6: c8f44b1e-242c-43c7-ac37-e18f1852b725
A7: Q02 | B7: Direct evidence retrieval | C7: Easy | D7: Measurement / monitoring | E7: What measurement approaches are used for atmospheric microplastics, and what are the implications for policy design? | F7: DOC109 DOC 030DOC111 DOC095 DOC017 | G7: Lack of standardisation, differing size thresholds and montering systesm so the answer should considers this when comparing diffent aproaches . | H7: Should separate identifcation and collection sections and desigus the comparitbilty between studies and the fact that is is limited and ther is no standised montering system in the courpus | I7: DOC030::chunk::2; DOC078::chunk::271; DOC014::chunk::179; DOC041::chunk::32; DOC078::chunk::232; DOC095::chunk::63 | J7: none | K7: 179 | L7: 1.861 | M7: 1937 | N7: 267 | O7: 0.00601 | P7: 2 | Q7: 2 | R7: 2 | S7: 2 | T7: 2 | U7: 2 | V7: 2 | W7: 21 | X7: =IF(COUNT(P7:V7)=0,"",SUM(P7:V7)) -> 14 | Y7: =IF(X7="","",X7/21) -> 0.66666667 | Z7: Covers collection and identification, and whether results can be compared. | AA7: **Scientific Evidence:** Atmospheric microplastics (AMPs) are measured using both active and passive sampling methods. Passive methods, such as deposition collectors, are most commonly used, while active methods include rain samplers, fallout collectors, and particulate (pump) samplers, which are particularly effective for quantifying suspended particles [DOC041::chunk::32]. Analytical identification relies on techniques like stereomicroscopy, Fourier transform infrared spectroscopy, Raman spectroscopy, and scanning electron microscopy, with emerging methods including laser direct infrared spectroscopy and thermochemical analysis coupled with mass spectrometry [DOC030::chunk::2]. Particle size distributions show that most atmospheric microplastic fibres are between 100–500 μm, with fragments often <100 μm [DOC095::chunk::63]. However, models for AMP emission, transport, and deposition are still in early development, and measurement approaches vary in sensitivity and specificity, leading to inconsistencies and gaps in data comparability [DOC030::chunk::2]. **Policy Implications:** The variability and early stage of measurement and modelling approaches highlight the need for standardised methods and robust monitoring to inform effective policy design. Current limitations mean that policy evaluation and adaptation should be iterative and evidence-based [DOC078::chunk::271]. Further research is needed to improve comparability and reliability of AMP data. | AB7: 2204 | AC7: d3e4eb51-9226-4be1-8850-d071ae64556c
A8: Q03 | B8: Direct evidence retrieval | C8: Medium | D8: Transport / deposition | E8: What is the evidence for atmospheric transport and deposition of microplastics, and what does this imply for considering long-term pollution? | F8: DOC058 DOc035 DOc005 DOc023 DOC091 | G8: magnitues are not well established as well as estimate range by upto 4 orders of manigitue DOC059: "no one has yet published a comprehensive size distribution for microplastics smaller than 10 µm" | H8: seperates the quantitive findings from the qualittive ones and make refercne th oth range in orders of mangitude. And that the deposisition estiamtes are demandands on the models used | I8: DOC002::chunk::71; DOC014::chunk::223; DOC016::chunk::212; DOC095::chunk::78; DOC059::chunk::107; DOC106::chunk::137 | J8: none | K8: 166 | L8: 2.098 | M8: 2471 | N8: 266 | O8: 0.00707 | P8: 2 | Q8: 2 | R8: 1 | S8: 2 | T8: 2 | U8: 1 | V8: 2 | W8: 21 | X8: =IF(COUNT(P8:V8)=0,"",SUM(P8:V8)) -> 12 | Y8: =IF(X8="","",X8/21) -> 0.57142857 | Z8: No made-up citations this time. But a calim comes froma. Page of referances. | AA8: **Scientific Evidence:** Multiple studies confirm that microplastics are present in the atmosphere across urban, rural, and remote regions, demonstrating significant potential for long-range atmospheric transport and deposition [DOC095::chunk::78]. Atmospheric transport is identified as a major pathway for microplastics to reach remote areas, including mountain catchments and the marine atmosphere [DOC002::chunk::71]; [DOC059::chunk::107]. Fibres and fragments are the most common forms detected. Deposition occurs via both dry and wet processes, influenced by wind, snowfall, and weathering [DOC095::chunk::78]. However, research is still in early stages, with insufficient standardized data on abundance, composition, and size distribution, especially in remote locations [DOC095::chunk::78]. There is agreement on the persistence and mobility of microplastics, but gaps remain regarding their long-term environmental fate and health impacts [DOC016::chunk::212]. **Policy Implications:** The evidence supports considering atmospheric microplastics as a long-term, transboundary pollutant. However, limitations in data comparability and knowledge of health effects mean that further research and standardized monitoring are needed before setting specific long-term pollution guidelines [DOC095::chunk::78]; [DOC016::chunk::212]. Final decisions should account for these uncertainties. | AB8: 2737 | AC8: 2097b037-2991-4625-991d-12c6ecdae384
A9: Q04 | B9: Direct evidence retrieval | C9: Medium | D9: Human health / exposure | E9: What evidence is there about human exposure to atmospheric microplastics, and what are the main limitations policymakers should be aware of? | F9: DOC017,DOC018 Doc 021(inhillantion) DOC046,DOC025,D0c043 (toxicoligy), DOC014 (evidance review). DOC063(microplasics in lung tissue). DOC0112,Doc113 (Uk indoor expsoure menasurments | G9: that there is insufficnet evdiance to acess the helth risks and there isnt an indefited relationships between quantities and health affects\. Exposure is given but harm isnt. That toxicoluge is on cells no peope. And could be work place realted not atmophere wedont know | H9: give clear evidance shoes there isnt a defined risk acessment to carry out and dsont convernt findings on animlas in human findings. as well as giving a good policy maker overview. | I9: DOC014::chunk::239; DOC095::chunk::74; DOC014::chunk::241; DOC033::chunk::2; DOC093::chunk::4; DOC035::chunk::6 | J9: none | K9: 174 | L9: 2.092 | M9: 2054 | N9: 269 | O9: 0.00626 | P9: 2 | Q9: 2 | R9: 1 | S9: 2 | T9: 3 | U9: 2 | V9: 2 | W9: 21 | X9: =IF(COUNT(P9:V9)=0,"",SUM(P9:V9)) -> 14 | Y9: =IF(X9="","",X9/21) -> 0.66666667 | Z9: Accurate and well supported. Same keyword isseus as system 1 | AA9: **Scientific Evidence:** There is growing evidence that humans are exposed to atmospheric microplastics, particularly in urban areas where concentrations are higher [DOC093::chunk::4]. Microplastics have been detected in atmospheric fallout in cities, with synthetic textile fibres being the dominant type [DOC033::chunk::2]. These airborne microplastics can be inhaled, and fibres have been found in the lower regions of human lungs [DOC093::chunk::4]. Occupational exposure in plastic processing factories has been linked to respiratory symptoms such as coughing and asthma [DOC095::chunk::74]. Inhalation is a concern, especially for industry workers, and dust ingestion may be a significant exposure route for young children [DOC095::chunk::74]. However, the actual health risks remain uncertain, as little is known about the effects of microplastics on human health and exposure levels [DOC014::chunk::241]. **Limitations and Gaps:** Key limitations include incomplete knowledge about exposure levels, health effects, and the lack of harmonised measurement methods [DOC014::chunk::241]. Most studies are limited in scope and geographic coverage, and there is considerable uncertainty about real risks [DOC014::chunk::241; DOC035::chunk::6]. Policymakers should be aware that current evidence is insufficient for definitive risk assessment. | AB9: 2323 | AC9: 65aaf3f5-072f-4f79-80dc-4f1c61b1c369
A10: Q05 | B10: Multi-source & cross-topic synthesis | C10: Medium | D10: Sources + transport | E10: What does the evidence suggest about interventions regarding the source-to-deposition pathway? | F10: DOC003,005,002 (sources of microplassitcs and the atomphere cycle) DOC034,058,029 (transport). DOC073,065,073(what the uk and eu is curnety doing DOc022, 108 (interviention modeling ) | G10: none of the papers actually rank the interventions they just give solutions as there is no review in the coupus, thre are different orders of mannuture in the transport sections so this needs to be comunicated clearly | H10: shows clearnly the different stages as well as keeping clear and traspanrtry to the souces. Keeping the actualy evideance of wahts going on sepreatate from the findings about possible interventions. Showuldn show where to intervene and diffent oiptions but not suggest a best option | I10: DOC014::chunk::240; DOC091::chunk::37; DOC014::chunk::49; DOC105::chunk::52; DOC038::chunk::77; DOC029::chunk::33 | J10: none | K10: 168 | L10: 1.903 | M10: 1877 | N10: 238 | O10: 0.00566 | P10: 2 | Q10: 2 | R10: 2 | S10: 2 | T10: 2 | U10: 1 | V10: 1 | W10: 21 | X10: =IF(COUNT(P10:V10)=0,"",SUM(P10:V10)) -> 12 | Y10: =IF(X10="","",X10/21) -> 0.57142857 | Z10: still dosnt day about the ranking issues | AA10: Scientific evidence indicates that atmospheric transport is a major pathway for microplastics (MPs) from source to deposition, with MPs found in both urban and remote locations at similar rates, suggesting that even ‘pristine’ areas are affected by long-range atmospheric transport [DOC091::chunk::37]. Sources include urban activities, car tyres, plastic-based textiles, household dust, and sewage effluents, with atmospheric deposition acting as an entry pathway for MPs to land, freshwater, and marine environments [DOC014::chunk::49]. The processes governing atmospheric transport, deposition, and dispersion are not yet fully understood, and there is a scarcity of information on the mechanisms and rates of MP movement in the atmosphere [DOC038::chunk::77]. Back-tracing and modeling approaches can help identify sources and transport routes, but current methods often oversimplify source attribution and do not fully account for the diversity of MP morphologies and transport dynamics [DOC029::chunk::33]. Policy implications: The complexity and incomplete understanding of atmospheric MP transport highlight the need for multidisciplinary approaches and further research before specific interventions can be reliably targeted along the source-to-deposition pathway [DOC014::chunk::240]. | AB10: 2115 | AC10: 57c5bb55-6b70-41a7-ba95-b78cdf4c0a90
A11: Q06 | B11: Multi-source & cross-topic synthesis | C11: Hard | D11: Exposure + human health | E11: What does the current evidence on atmospheric microplastics suggest in terms of the human health impacts, and its relevance for policy consideration? | F11: DOC017, 018 (Committee on the Medical Effects of Air Pollutants ). DOC021(inhilantion). DOC014(Science Advice for Policy by European Academies review) DOC045, 025, 043 (toxicoligy) DOC063 ( Micorpstics in lungs) DOC0112,113 (Uk indoor expsoure menasurments | G11: comeap finds insufficne evidance to acess the health risks as there is no dose relatships. As well as Sepea finds no evidance of widespready risk however its from 2019 outdie courpus range | H11: give clear evidance shoes there isnt a defined risk acessment to carry out and dsont convernt findings on animlas in human findings. as well as giving a good policy maker overview. | I11: DOC014::chunk::239; DOC095::chunk::74; DOC052::chunk::12; DOC095::chunk::9; DOC017::chunk::17; DOC093::chunk::4 | J11: none | K11: 195 | L11: 2.07 | M11: 1821 | N11: 293 | O11: 0.00599 | P11: 2 | Q11: 2 | R11: 2 | S11: 2 | T11: 3 | U11: 2 | V11: 2 | W11: 21 | X11: =IF(COUNT(P11:V11)=0,"",SUM(P11:V11)) -> 15 | Y11: =IF(X11="","",X11/21) -> 0.71428571 | Z11: better than system 1 Uses the UK information apropratly | AA11: **Scientific Evidence:** Current evidence indicates widespread presence of atmospheric microplastics (MPs) in urban, suburban, and remote areas, with indoor dust identified as a significant source of human exposure [DOC095::chunk::9]. MPs have been detected in the lower regions of human lungs, suggesting inhalation is possible, especially in urban populations [DOC093::chunk::4]. Epidemiological studies link ambient particulate air pollution to adverse respiratory and cardiovascular effects, but direct evidence for MPs is limited [DOC095::chunk::74]. Toxicological studies show that MPs deposited in the lung may induce oxidative stress, inflammation, and cytotoxicity, but these findings are based on limited data, often using unrealistically high exposure concentrations and poorly characterized particles, reducing their relevance to real-world exposures [DOC017::chunk::17]. There is also evidence that MPs can carry toxic pollutants, potentially increasing health risks [DOC093::chunk::4]. However, comprehensive evaluations and systematic overviews of health impacts, especially in specific regions like India, remain lacking [DOC052::chunk::12]. **Policy Relevance:** The evidence base is incomplete and characterized by significant uncertainties regarding exposure levels, toxicological pathways, and real-world health impacts of atmospheric MPs [DOC014::chunk::239]; [DOC017::chunk::17]. This limits the ability to predict risks or evaluate policy options effectively. Further research and monitoring are needed before robust policy recommendations can be made. | AB11: 2114 | AC11: 43ca7d0b-1e52-4461-a8d4-c5e19e255dc9
A12: Q07 | B12: Multi-source & cross-topic synthesis | C12: Hard | D12: Deposition + ecology | E12: How does atmospheric deposition cause atmospheric microplastics to reach ecosystems, and what remains uncertain? | F12: DOC027 ( desposition to wetlands) DOC049 (ecoligcal risks) DOC103, 104, 026 ( soil and plants) DOC105 (unknown aspects of plastic pollution) DOC050 , 062 (deposistion measruments) | G12: the coupus mainly focuses on deposisiton there isnt much evidance about the impact of this deposiston of microplastics on ecosystems | H12: must speerate the effects form the effects evidance . And must note that the concetations used in the lab soil expements is much higher than that was ovserved in the field.. | I12: DOC027::chunk::4; DOC095::chunk::69; DOC005::chunk::5; DOC014::chunk::110; DOC053::chunk::24; DOC027::chunk::6 | J12: none | K12: 188 | L12: 2.024 | M12: 1901 | N12: 313 | O12: 0.00631 | P12: 2 | Q12: 2 | R12: 2 | S12: 2 | T12: 3 | U12: 2 | V12: 2 | W12: 21 | X12: =IF(COUNT(P12:V12)=0,"",SUM(P12:V12)) -> 15 | Y12: =IF(X12="","",X12/21) -> 0.71428571 | Z12: Figures correct and it adresses that ransport is poorly understood. | AA12: **Scientific Evidence:** Atmospheric deposition is a major pathway by which microplastics reach various ecosystems, including wetlands, oceans, and remote regions. Microplastics are transported by wind and can be deposited through rainfall or snowfall, allowing them to reach even remote areas such as glaciers and the Arctic, far from local plastic sources [DOC095::chunk::69]. Studies indicate that atmospheric deposition can contribute more microplastics to aquatic environments than riverine or wastewater sources, with wetlands acting as significant sinks for these particles [DOC027::chunk::4]. Deposition rates vary widely, with estimates for remote areas ranging from 50 to 700 plastics m⁻²·d⁻¹, and up to 22,000 tons deposited annually across the contiguous United States [DOC005::chunk::5]. However, the mechanisms of microplastic emission to the atmosphere, their transport dynamics, and the influence of socio-environmental factors remain poorly understood [DOC053::chunk::24]; [DOC027::chunk::6]. Quantitative data on fluxes, distribution, and ecological effects are limited, and detection methods are still evolving [DOC027::chunk::6]; [DOC014::chunk::110]. **Possible Policy Implications:** Current evidence highlights the need for improved monitoring and understanding of atmospheric microplastic transport and deposition, but significant uncertainties remain regarding sources, pathways, and impacts [DOC027::chunk::6]; [DOC053::chunk::24]; [DOC014::chunk::110]. Final policy decisions should consider these knowledge gaps. | AB12: 2214 | AC12: 98faea97-04a2-426b-aa4d-b65747cbbdf1
A13: Q08 | B13: Multi-source & cross-topic synthesis | C13: Hard | D13: Measurement + evidence interpretation | E13: How do differences in sampling and methods affect comparison of atmospheric microplastic evidence to inform policy? | F13: DOC109(chemical anlyais) DOC030 ( anlyalitcal methods) DOC111(anlyasis of deposition) DOC095(standarisation gaps) DOC017(Commitee of the medical effects of air polutants) DOC090, 061, 064 (sampling studies) | G13: there is no standissed method and comparitson is dificulrt as there is deiiffernt collection,processing andn alyltical methods across all of the studies | H13: explain the diffrenty methods, and not compairing figures from from the studdies directly as they are from diffent tecniques and there is no standised method and dosent recommend a montering method/ standards that’s not in the coupus. | I13: DOC033::chunk::31; DOC030::chunk::43; DOC003::chunk::7; DOC021::chunk::86; DOC006::chunk::15; DOC095::chunk::79 | J13: none | K13: 174 | L13: 2.425 | M13: 1496 | N13: 303 | O13: 0.00542 | P13: 2 | Q13: 2 | R13: 2 | S13: 2 | T13: 3 | U13: 3 | V13: 2 | W13: 21 | X13: =IF(COUNT(P13:V13)=0,"",SUM(P13:V13)) -> 16 | Y13: =IF(X13="","",X13/21) -> 0.76190476 | Z13: Strong answer | AA13: Scientific evidence: There is broad agreement that differences in sampling and analytical methods significantly hinder the comparability of atmospheric microplastic (MP) studies. Variations in sampling techniques, analytical approaches, and reporting units make it difficult to compare results across studies or to relate findings to air quality guidelines and health effect thresholds [DOC003::chunk::7]; [DOC021::chunk::86]; [DOC030::chunk::43]; [DOC033::chunk::31]; [DOC095::chunk::79]. For example, some methods only detect MPs above certain sizes (often >10 or >50 μm), leaving the respirable fraction (<2.5 μm) largely unquantified [DOC021::chunk::86]; [DOC033::chunk::31]. Passive and active sampling methods each have strengths and limitations, and environmental factors such as weather can further affect results [DOC006::chunk::15]. The lack of standardized protocols for sampling, identification, and data reporting prevents reliable comparison, meta-analysis, and risk assessment [DOC030::chunk::43]; [DOC095::chunk::79]. Policy implications (based strictly on evidence): Current evidence is insufficient for robust policy comparison or risk assessment due to methodological inconsistencies and data gaps, especially regarding small particle sizes and human exposure [DOC021::chunk::86]; [DOC033::chunk::31]; [DOC095::chunk::79]. Standardization is identified as a critical need for future research. Final policy decisions should consider these limitations. | AB13: 1799 | AC13: 10dc74e4-5b66-4c31-857b-02bebe034f61
A14: Q09 | B14: Conflicting evidence & comparison | C14: Medium | D14: Measurement / monitoring | E14: How much do reported concentrations of atmospheric microplastics differ between environments and why? | F14: DOC095 (spread) DOC090 (weser,germany cathcment) DOC061, 113 (humber UK Indoors and Outdoors) DOC112, (Birmingham Indoor air) DOC041, 051 (forest urban rural) DOC030, 109 ( Explain variation) | G14: much of the information in the coupus on this topic is mearly methodoligy and some of the reptored concentrations differ by upto a thousnad times. And the spectromatry and mass spectromatry results and not comparible as one gives how many the other how much. and spectornomy hasa. floor in hte sizes it can detect of around 10um as anyhting below this is not noticeable in most studies. | H14: Reoports a rang of different reuslts and making sure to state the differnces in methods as well as sepesrating the differances caused by the diffrent envroments from the differances in methods | I14: DOC095::chunk::41; DOC003::chunk::81; DOC095::chunk::63; DOC003::chunk::62; DOC024::chunk::17; DOC053::chunk::37 | J14: none | K14: 162 | L14: 1.882 | M14: 2056 | N14: 285 | O14: 0.00639 | P14: 2 | Q14: 2 | R14: 2 | S14: 2 | T14: 2 | U14: 2 | V14: 2 | W14: 21 | X14: =IF(COUNT(P14:V14)=0,"",SUM(P14:V14)) -> 14 | Y14: =IF(X14="","",X14/21) -> 0.66666667 | Z14: explains why methods differ and also fixes the error of units from previous system | AA14: **Scientific Evidence:** Reported concentrations of atmospheric microplastics are significantly higher indoors than outdoors. Studies show indoor air contains 6 to 6.5 times more microplastics than outdoor air, with indoor concentrations ranging from 1.0 to 60.0 fibres/m³ and outdoor concentrations from 0.3 to 1.5 fibres/m³, though some outdoor sites (e.g., Surabaya, Indonesia) report up to 174 particles/m³ [DOC095::chunk::41]; [DOC003::chunk::81]. The dominant size range is 100–300 μm, with fibres and fragments most common [DOC053::chunk::37]; [DOC095::chunk::63]. Indoor microplastics are linked to indoor sources and occupant activities, while outdoor concentrations are highest near industrial and urban areas [DOC053::chunk::37]. Outdoor microplastics are generally smaller and less variable than indoor ones [DOC003::chunk::81]; [DOC095::chunk::63]. Methodological differences and lack of standardization limit direct comparisons, though harmonization is improving [DOC095::chunk::41]. **Policy Implications:** Evidence suggests indoor environments are a major source of atmospheric microplastics, and concentrations vary by location and human activity. However, methodological limitations and data gaps remain, especially regarding standardization and global comparability. Final policy decisions should consider these uncertainties. | AB14: 2341 | AC14: a14e1d74-c0fa-4cca-9d3f-f1d3f95facd0
A15: Q10 | B15: Conflicting evidence & comparison | C15: Hard | D15: Sources / intervention relevance | E15: How consistent is the evidence that tyre wear is a major source of atmospheric microplastics, and how reliable are current estimates of its contribution to the problem? | F15: DOC003, 109 (cover tyre wear) DOC005 (Emission figures) DOC034, 047, 038, 045 ( reviews that mention tyrewear) DOC022 (estimates tyre loss from trafic data) | G15: the estimates dissagreee with DOc003 saying 84% of airmbone plastics come from road use. Howevern doc 005 says 96Gg of micro plastics aare entering long range transport from tyres. But them DOC0109 notes that tyres are only 40-60% poylomer so what dos actually count as a micro plastic nedes to be considerd | H15: tyre ware needs to be mentiond as one of the major couases of atmopeheric micro plastics but that the soruces give confliction results int terms of estimates. | I15: DOC038::chunk::28; DOC035::chunk::33; DOC003::chunk::45; DOC077::chunk::79; DOC038::chunk::26; DOC022::chunk::131 | J15: none | K15: 171 | L15: 1.922 | M15: 2278 | N15: 256 | O15: 0.0066 | P15: 2 | Q15: 2 | R15: 2 | S15: 2 | T15: 3 | U15: 2 | V15: 2 | W15: 21 | X15: =IF(COUNT(P15:V15)=0,"",SUM(P15:V15)) -> 15 | Y15: =IF(X15="","",X15/21) -> 0.71428571 | Z15: Figures correct. And esplains why why estimates vary. | AA15: **Scientific Evidence:** Multiple sources consistently identify tyre wear as a major source of atmospheric microplastics (MPs). Tyre wear contributes significantly to airborne MPs, with estimates suggesting 0.1–10% of PM10 and 3–7% of PM2.5 in the atmosphere are tyre-derived particles [DOC038::chunk::26]. Global calculations estimate that 146,000 to 2,907,000 tonnes of tyre wear MPs become airborne annually, though these figures vary due to methodological differences [DOC003::chunk::45]. Tyre wear emissions are especially high in urban areas but can be transported long distances, even reaching remote regions like the Arctic [DOC022::chunk::131]. However, the reliability of these estimates is limited by analytical challenges: current methods often fail to distinguish tyre wear MPs from other particles, and compositional analysis is needed for accurate identification [DOC035::chunk::33]. Ongoing research aims to address these gaps [DOC077::chunk::79]. **Policy Implications:** While evidence strongly supports tyre wear as a major atmospheric MP source, uncertainties in quantification and identification remain. Further research and improved analytical methods are needed before precise regulatory action can be based on current estimates. Final decisions should consider these limitations. | AB15: 2534 | AC15: f95e6590-322f-41b7-a080-9665470a22a2
A16: Q11 | B16: Conflicting evidence & comparison | C16: Hard | D16: Transport / spatial scale | E16: What is agreed and what is disputed in the long-range transport of atmospheric microplastics, and how do transport estimates disagree in terms of scale? | F16: DOC058 (long term transport) DOC034 (remote region transport DOC005 (uncertantcys for transport and deposisiton) DOC029 (trasport in asia) DOC059 (atmopshertic Modeling) DOC095, 047 (Reviews) | G16: it is genrally agreed that trasport does occour to remote regions. But the sale is not this needs to be reflected in the answer | H16: it needs to show that trasport does occour even to remote rgions and make it clear that there is no definitive view on the scale. | I16: DOC005::chunk::21; DOC047::chunk::23; DOC058::chunk::0; DOC014::chunk::53; DOC035::chunk::34; DOC014::chunk::54 | J16: none | K16: 227 | L16: 2.399 | M16: 1954 | N16: 347 | O16: 0.00668 | P16: 2 | Q16: 2 | R16: 2 | S16: 2 | T16: 3 | U16: 3 | V16: 2 | W16: 21 | X16: =IF(COUNT(P16:V16)=0,"",SUM(P16:V16)) -> 16 | Y16: =IF(X16="","",X16/21) -> 0.76190476 | Z16: Separates agreed and disputed claims | AA16: **Scientific Evidence:** There is broad agreement that atmospheric microplastics (MPs) can undergo long-range transport, reaching remote regions such as Antarctica and the Southern Ocean [DOC058::chunk::0]. Studies consistently find that morphology, especially fibers, plays a dominant role in transport efficiency, with fibers being transported more efficiently than fragments [DOC058::chunk::0]. The atmosphere is recognized as a notably faster pathway for small micro- and nanoplastics (MnP) compared to rivers, and can deposit substantial amounts into marine and terrestrial environments, including remote areas [DOC047::chunk::23]. However, there are significant uncertainties and disagreements regarding the scale of transport. For example, global emission estimates for long-range transported MPs from tire wear and braking vary widely, from 96 [63 to 110] Gg·y⁻¹ to 284 (102 to 787) Gg·y⁻¹, depending on assumptions about particle size and fraction available for transport [DOC005::chunk::21]. There is also a large knowledge gap about MP occurrence and burden in the marine boundary layer, and limited validation of transport models [DOC058::chunk::0]; [DOC014::chunk::53]. Local versus remote influences on deposition are debated, with urban areas dominated by local sources and remote areas more affected by meteorological transport [DOC035::chunk::34]. **Policy Implications:** While atmospheric transport of MPs is established, the wide range in emission estimates and limited data on transport mechanisms and deposition rates highlight substantial uncertainties. Further research is needed to refine models and quantify fluxes before robust regulatory decisions can be made [DOC014::chunk::53]; [DOC035::chunk::34]. | AB16: 2301 | AC16: 35012f87-6bfb-49a5-accf-ce86d23c45eb
A17: Q12 | B17: Conflicting evidence & comparison | C17: Hard | D17: UK relivance | E17: What existing UK policy instruments address microplastics, and do any of them cover atmospheric sources? | F17: DOC075 (packaging tax) DOC073 (Single Use bans) DOC072 (Microbeads) DOC084 Producer responcibilty) DOC078 (Air quality stratagy) DOC089 (Clean air zones) DOC077, 078, 082,088 (curnet uk strategys) | G17: there is a clear gap as ther is nothing in the coupus that links atmopsheric. As it does not fall under the efford to regualte particualte matter but ithis is mainly focused on pm 2.5 | H17: indentifyes a clear gap in the lesgisaltion | I17: DOC020::chunk::445; DOC035::chunk::2; DOC014::chunk::240; DOC059::chunk::1; DOC014::chunk::33; DOC035::chunk::6 | J17: none | K17: 180 | L17: 2.805 | M17: 1907 | N17: 254 | O17: 0.00585 | P17: 2 | Q17: 2 | R17: 2 | S17: 2 | T17: 2 | U17: 2 | V17: 1 | W17: 21 | X17: =IF(COUNT(P17:V17)=0,"",SUM(P17:V17)) -> 13 | Y17: =IF(X17="","",X17/21) -> 0.61904762 | Z17: Says there's no evidence of UK rules. No made-up laws. | AA17: **Scientific Evidence:** Current scientific reviews highlight that microplastics are a widespread contaminant in both aquatic and terrestrial environments, with recent studies confirming their presence in atmospheric deposition in urban centres such as London [DOC035::chunk::2]. Airborne microplastics can be transported over long distances, including to remote regions, and are present throughout the troposphere, with smaller particles even reaching the lower stratosphere [DOC059::chunk::1]. Despite these findings, the evidence base on the quantities, characteristics, and pathways of airborne microplastics remains sparse, especially regarding their sources and impacts in the UK [DOC035::chunk::6]. Comprehensive reviews note that while there are various policies addressing microplastics in general, there is a lack of clarity and limited evidence on whether existing UK policy instruments specifically address atmospheric microplastic sources [DOC014::chunk::240]. The complexity of the issue and the need for multidisciplinary approaches are emphasized, but no direct evidence of UK policy instruments targeting atmospheric microplastics is provided [DOC014::chunk::33]. **Policy Implications:** There is insufficient evidence to confirm that current UK policy instruments explicitly cover atmospheric microplastic sources. Further policy analysis and research are needed. Final decisions remain with the policymaker. | AB17: 2161 | AC17: 6f2b712d-f648-42ba-8055-ad224a429c34
... A20: Q15 | B20: Evidence strength & uncertainty | C20: Hard | D20: Ecological impacts | E20: How strong is the evidence that atmospheric microplastic deposition has a detrimental ecological impact, and what evidence gaps limit policy action? | F20: DOC027 (wetland deposition), DOC050, 062 (deposition measurement) DOC049 (ecological risks) DOC036 (environmental fate and impacts) DOC103 (soil properties), DOC104 (soil carbon cycling. DOC026 (lettuce stress response), DOC105 (meta-analysis of known and unknown effects). | G20: bothe deposistona nd the effectson are both disgiussed and measured in the coupus however there isnt a study that recectaly links and compairs them | H20: well written and distuagised the differtnce from field observations and and lab stuidies. | I20: DOC035::chunk::36; DOC005::chunk::42; DOC014::chunk::241; DOC005::chunk::38; DOC014::chunk::9; DOC027::chunk::4 | J20: none | K20: 195 | L20: 2.236 | M20: 1770 | N20: 296 | O20: 0.00591 | P20: 2 | Q20: 2 | R20: 2 | S20: 1 | T20: 2 | U20: 2 | V20: 2 | W20: 21 | X20: =IF(COUNT(P20:V20)=0,"",SUM(P20:V20)) -> 13 | Y20: =IF(X20="","",X20/21) -> 0.61904762 | Z20: Accurate, honest that risk is unproven. Doesn't separate lab from field. =. Poor systherisis | AA20: **Scientific Evidence:** There is evidence that atmospheric microplastic deposition is widespread, with microplastics detected in all urban samples studied and deposition rates increasing alongside plastic production and use [DOC035::chunk::36]; [DOC027::chunk::4]. Atmospheric deposition is now recognized as a major source of microplastics to aquatic ecosystems, sometimes surpassing wastewater inputs [DOC027::chunk::4]. Some studies indicate that microplastics may accumulate in soils and plants, with negative effects on plant yield and nutrient availability observed in certain cases [DOC005::chunk::42]. However, the overall ecological and human health risks remain highly uncertain. While there may be specific locations where microplastic concentrations exceed predicted no-effect levels, widespread or general ecological risks have not been conclusively demonstrated [DOC014::chunk::241]. The toxicity of microplastics relative to other aerosols is also not well understood [DOC005::chunk::42]. **Evidence Gaps and Limitations:** Major gaps include limited understanding of the fate, transport, and sources of atmospheric microplastics, insufficient harmonization of measurement methods, and a lack of clarity on exposure effects for biota and humans [DOC035::chunk::36]; [DOC014::chunk::241]. There is also little knowledge about threshold concentrations for negative ecosystem impacts [DOC005::chunk::42]. These uncertainties constrain the ability to assess risks and design targeted policy interventions. Final policy decisions should account for these evidence gaps. | AB20: 2066 | AC20: bf19a14a-3781-4260-b698-e5d52f6e07ab
A21: Q16 | B21: Evidence strength & uncertainty | C21: Hard | D21: Transport | E21: Is there evidence that atmospheric microplastic concentrations are increasing? | H21: should keep the solid conclusions apart from the bits where the scale or the mechanism is still uncertain. | I21: DOC035::chunk::6; DOC093::chunk::4; DOC016::chunk::214; DOC059::chunk::60; DOC003::chunk::71; DOC016::chunk::69 | J21: none | K21: 182 | L21: 2.047 | M21: 1833 | N21: 249 | O21: 0.00566 | P21: 2 | Q21: 3 | R21: 2 | S21: 2 | T21: 3 | U21: 3 | V21: 2 | W21: 21 | X21: =IF(COUNT(P21:V21)=0,"",SUM(P21:V21)) -> 17 | Y21: =IF(X21="","",X21/21) -> 0.80952381 | Z21: much better than system 1 | AA21: **Scientific Evidence:** Multiple sources indicate that atmospheric microplastic concentrations are expected to increase, though direct long-term observational data are limited. Model projections show that with global plastic production set to rise, microplastic emissions and their atmospheric concentrations are also expected to grow, especially in urban areas where sources such as tyre wear and textile fibres are concentrated [DOC059::chunk::60]. Observational studies confirm the presence of microplastics in urban air and suggest higher concentrations in cities compared to remote areas, but there is a paucity of long-term data quantifying trends over time [DOC035::chunk::6]; [DOC093::chunk::4]. Some evidence suggests temporal and seasonal variability in concentrations, but it is unclear if there is a consistent upward trend due to limited monitoring [DOC003::chunk::71]. Overall, while models and indirect evidence point to increasing concentrations, robust long-term empirical data are lacking, representing a significant knowledge gap [DOC016::chunk::214]. **Policy Implications:** The lack of comprehensive long-term monitoring data limits the ability to assess trends and risks fully. Caution is warranted in interpreting current evidence, and further research and monitoring are needed to clarify trends and potential impacts. Final decisions remain with policymakers. | AB21: 2082 | AC21: fcdfd78f-5432-41cd-8f04-bdbffdb1342e
A22: Q17 | B22: Insufficient / out-of-scope | C22: Medium | D22: Sources / prioritisation | E22: Does the evidence allow one atmospheric microplastic source to be identified definitively as the highest priority for intervention? | G22: that there is no papers that ranks scoures of amps in tersm what waht is the main cuse. And stiddies state that there is an increase in certain areas but there isnt an exasutuve comparitve review | H22: says no and explains estimates disagree so ranking sources instead of just picking one. | I22: DOC014::chunk::259; DOC055::chunk::114; DOC030::chunk::50; DOC070::chunk::32; DOC022::chunk::356; DOC030::chunk::10 | J22: none | K22: 154 | L22: 1.987 | M22: 2319 | N22: 215 | O22: 0.00636 | P22: 2 | Q22: 2 | R22: 1 | S22: n/a | T22: n/a | U22: 3 | V22: 2 | W22: 15 | X22: =IF(COUNT(P22:V22)=0,"",SUM(P22:V22)) -> 10 | Y22: =IF(X22="","",X22/15) -> 0.66666667 | Z22: Says no and explains why but Cites the same reference list as System 1. | AA22: Scientific evidence does not currently allow one atmospheric microplastic source to be definitively identified as the highest priority for intervention. Multiple studies confirm the presence of microplastics in both indoor and outdoor air, with hotspots in densely populated areas and even detection in remote regions, indicating diverse and widespread sources [DOC030::chunk::10]. Atmospheric transport is recognized as a major pathway for microplastics to reach remote environments, but the relative contributions of specific sources (e.g., textiles, urban dust, industrial emissions) remain unclear [DOC055::chunk::114]; [DOC030::chunk::50]. Furthermore, there is a lack of standardised methods for exposure and hazard characterisation, and quantitative data are often insufficient in quality, making it impossible to conclude with certainty which sources pose the greatest risk [DOC014::chunk::259]. This highlights significant gaps and limitations in current knowledge. Policy implications: Decisions on prioritising interventions should be made cautiously, as the evidence base is not yet robust enough to single out one source for targeted action [DOC014::chunk::259]. | AB22: 2534 | AC22: 8932b1c6-c11a-4ac9-b2c3-ab158e066ae3
A23: Q18 | B23: Insufficient / out-of-scope | C23: Hard | D23: Human health / standards | E23: Does the current evidence support a safe atmospheric exposure threshold for microplastics that can be applied in policy or regulation? | G23: comeap says you cant describe a dose response relationship without exposure, epidemiology and toxicology data. And this woild be needed to create a robust threshold. | H23: must not use or suggest the pm2.5 measnuremtns that are fonud in the who doucments as this is for a different type of mesaurments. | I23: DOC108::chunk::214; DOC016::chunk::210; DOC016::chunk::214; DOC053::chunk::53; DOC106::chunk::162; DOC002::chunk::80 | J23: none | K23: 184 | L23: 1.731 | M23: 2005 | N23: 241 | O23: 0.00594 | P23: 2 | Q23: 3 | R23: 2 | S23: n/a | T23: n/a | U23: 3 | V23: 2 | W23: 15 | X23: =IF(COUNT(P23:V23)=0,"",SUM(P23:V23)) -> 12 | Y23: =IF(X23="","",X23/15) -> 0.8 | Z23: strong No safe limit can be set. | AA23: Scientific evidence indicates that there is currently no robust or universally accepted safe atmospheric exposure threshold for microplastics that can be applied in policy or regulation. Multiple sources highlight a lack of knowledge on what concentrations of microplastics are safe for the environment or human health, with proposed thresholds being tentative and not derived according to established chemical safety standards [DOC016::chunk::210]. The persistent and accumulating nature of microplastics means that even if a safe threshold could be identified, it would likely be exceeded over time [DOC108::chunk::214]. For atmospheric microplastics specifically, there is a paucity of research on toxicological effects and risks from inhalation at realistic exposure levels, and no regulation currently exists for microplastic contamination in air, food, or water [DOC053::chunk::53]. The absence of evidence for significant adverse impacts should not be interpreted as evidence of safety, and major data gaps remain, especially for nanoplastics and secondary exposure pathways [DOC016::chunk::214]. Policy implications: Current evidence is insufficient to define or support a safe atmospheric exposure threshold for microplastics. Further research and monitoring are needed before such thresholds can be established. Final decisions remain with policymakers. | AB23: 2246 | AC23: 028fe92c-6978-4585-9400-5c1f849c5678
A24: Q19 | B24: Insufficient / out-of-scope | C24: Easy | D24: Environmental policy outside corpus | E24: What does the evidence show about the effectiveness of nuclear power generation for reducing Norway's carbon emissions? | G24: there should be nothing as there is nothing on nroway or nuclea power in the coupus | H24: should be stated tahtthere isnt evidance on this in the corpus. | I24: DOC106::chunk::329; DOC088::chunk::175; DOC034::chunk::58; DOC077::chunk::91; DOC106::chunk::460; DOC107::chunk::65 | J24: none | K24: 136 | L24: 1.716 | M24: 2194 | N24: 196 | O24: 0.00596 | P24: 3 | Q24: 3 | R24: 2 | S24: n/a | T24: n/a | U24: 3 | V24: 2 | W24: 15 | X24: =IF(COUNT(P24:V24)=0,"",SUM(P24:V24)) -> 13 | Y24: =IF(X24="","",X24/15) -> 0.86666667 | Z24: strong answer states the lack of direct evidance | AA24: Scientific Evidence: None of the provided sources directly address the effectiveness of nuclear power generation for reducing Norway's carbon emissions. The available evidence discusses emissions from combustion plants, the impact of air pollutants from power generation, and strategies for reducing particulate matter and other pollutants, but does not mention nuclear power or its specific role in Norway’s energy mix or carbon emissions profile [DOC088::chunk::175]; [DOC077::chunk::91]; [DOC106::chunk::329]; [DOC106::chunk::460]; [DOC107::chunk::65]; [DOC034::chunk::58]. There is also no comparative analysis of nuclear power versus other energy sources in the context of Norway. Policy Implications: Due to the lack of direct evidence in the provided sources, no conclusions can be drawn about the effectiveness of nuclear power generation for reducing Norway's carbon emissions. Further evidence would be required to inform policy decisions on this topic. Final decisions remain with the human policymaker. | AB24: 2390 | AC24: 66eb14be-91e5-44fe-ba2d-dfbb3c654e13
A25: Q20 | B25: Insufficient or unanswerable from retrieved evidence | C25: Hard | D25: Adjacent microplastics policy | E25: What concentrations of microplastics have been measured in UK drinking water? | G25: the coupus does have UK tap water figures in DOC021 chunks 59 and 60, most of them below the limit of quantification. no system retrieved them so this is a retrieval fail not a gap in the coupus. | H25: it should say that the socurs have no UK measurements. | I25: DOC014::chunk::74; DOC021::chunk::295; DOC021::chunk::64; DOC109::chunk::276; DOC014::chunk::75; DOC033::chunk::5 | J25: none | K25: 172 | L25: 1.782 | M25: 2621 | N25: 254 | O25: 0.00727 | P25: 2 | Q25: 1 | R25: 1 | S25: n/a | T25: n/a | U25: 2 | V25: 1 | W25: 15 | X25: =IF(COUNT(P25:V25)=0,"",SUM(P25:V25)) -> 7 | Y25: =IF(X25="","",X25/15) -> 0.46666667 | Z25: Better than System 1. But one figure comes from a wildlife paper not drinking water. | AA25: Scientific evidence indicates that microplastics have been detected in UK drinking water, but concentrations vary and data are limited. Studies report microplastics in both bottled and tap water, with concentrations ranging from several particles per litre up to 10^6 particles/L, particularly for smaller particles (<300 µm) [DOC014::chunk::74]. A review by UK Water Industry Research highlights potential risks from microplastics in drinking water, but does not provide specific concentration values for the UK [DOC021::chunk::295]. Box plot data from multiple studies show that concentrations generally increase as particle size decreases, with the highest and most variable concentrations reported for particles between 1–5 µm [DOC021::chunk::64]. However, the quality and comparability of these studies are limited, and there is concern about whether all detected particles are truly microplastics [DOC021::chunk::64]. Overall, there is insufficient, high-quality, UK-specific data to provide a definitive concentration range for microplastics in UK drinking water [DOC014::chunk::75]. Policy implications: The lack of robust, UK-specific data and methodological limitations mean that exposure and risk assessments for microplastics in UK drinking water remain highly uncertain [DOC014::chunk::75]. | AB25: 2875 | AC25: c06b9e26-5293-4a34-92e3-1ac577649782
C27: In-scope mean (Q01-Q16, out of 21) | E27: Mean (Q01-Q16, out of 21) | X27: =IFERROR(AVERAGE(X6:X21),"") -> 14.25
C28: Out-of-scope mean (Q17-Q20, out of 15) | E28: Mean (Q17-Q20, out of 15) | X28: =IFERROR(AVERAGE(X22:X25),"") -> 10.5
C29: Overall mean % | E29: Overall mean % | Y29: =IFERROR(AVERAGE(Y6:Y25),"") -> 0.68285714

Sheet System 3 v2
A1: System 3 v2
F4: EXPECTED EVIDENCE | I4: WHAT THE SYSTEM DID | P4: SCORING
A5: Q ID | B5: Category | C5: Difficulty | D5: Topic area | E5: Question | F5: Expected corpus documents | G5: Expected uncertainty / disagreement | H5: Expected good behaviour | I5: Retrieved chunk IDs | J5: Invalid citations | K5: Words | L5: Seconds | M5: In tokens | N5: Paid tokens (both calls) | O5: Cost (USD) | P5: R | Q5: F | R5: G | S5: S | T5: D | U5: U | V5: P | W5: Out of | X5: Total | Y5: % | Z5: Scoring comments | AA5: Actual system output | AB5: Paid tokens | AC5: Audit run ID
A6: Q01 | B6: Direct evidence retrieval | C6: Easy | D6: Sources / emissions | E6: What are the main sources of atmospheric microplastics and which should be considered when considering emission-reduction policy interventions? | F6: DOC003,DOC002 DOC55DOC45 DOC52 DOC038 DOC05 DOC011 DOC29 | G6: Ther is some ambiguaty between parctile cizing as there is no stnadardised micropasitcs sizing method. They change with the method used and the testing envriomnet. | H6: should name the main sources and be clear where the coupus does or does not support prioritising them. Aswell as not giving a ranking as a ranking of the different methods is not given in the coupus. | I6: DOC046::chunk::29; DOC012::chunk::187; DOC052::chunk::33; DOC003::chunk::172; DOC108::chunk::284; DOC029::chunk::8 | J6: none | K6: 170 | L6: 39.057 | N6: 5088 | O6: 0.01361 | P6: 2 | Q6: 1 | R6: 2 | S6: 2 | T6: 3 | U6: 2 | V6: 2 | W6: 21 | X6: =IF(COUNT(P6:V6)=0,"",SUM(P6:V6)) -> 14 | Y6: =IF(X6="","",X6/21) -> 0.66666667 | Z6: Names the sources and admits the gaps. India problem persists | AA6: **Scientific Evidence:** Atmospheric microplastics originate from both primary and secondary sources. Primary sources directly emit microplastics into the air, including emissions from textiles, urban dust, traffic resuspension, industrial activities, and consumer products, with fibrous microplastics being especially prevalent in urban environments [DOC052::chunk::33]. Secondary sources result from the fragmentation and degradation of larger plastics, such as those from plastic articles, synthetic textiles, and road dust, as well as wind erosion from landfills, construction, and demolition sites [DOC046::chunk::29]; [DOC003::chunk::172]. Shipping and transportation industries, landfill wind erosion, and waste compaction are also potential contributors, but their quantitative impact remains unclear and requires further investigation [DOC003::chunk::172]. Nanoplastics can be primary (intentionally produced) or secondary (from degradation), with additional sources like mineral dust and sea salt particles [DOC046::chunk::29]. There are significant knowledge gaps regarding the full range and magnitude of these sources [DOC003::chunk::172]; [DOC108::chunk::284]. **Policy Implications:** Establishing baseline assessments to identify and quantify these sources is essential for effective emission-reduction interventions. Further research is needed to evaluate mitigation options and address knowledge gaps [DOC012::chunk::187]; [DOC108::chunk::284]. | AB6: 5088 | AC6: d77e4f56-541c-48ab-acb1-0133b6544dad
A7: Q02 | B7: Direct evidence retrieval | C7: Easy | D7: Measurement / monitoring | E7: What measurement approaches are used for atmospheric microplastics, and what are the implications for policy design? | F7: DOC109 DOC 030DOC111 DOC095 DOC017 | G7: Lack of standardisation, differing size thresholds and montering systesm so the answer should considers this when comparing diffent aproaches . | H7: Should separate identifcation and collection sections and desigus the comparitbilty between studies and the fact that is is limited and ther is no standised montering system in the courpus | I7: DOC030::chunk::2; DOC078::chunk::271; DOC014::chunk::179; DOC041::chunk::32; DOC078::chunk::232; DOC095::chunk::63 | J7: none | K7: 147 | L7: 38.235 | N7: 5255 | O7: 0.01363 | P7: 3 | Q7: 2 | R7: 2 | S7: 2 | T7: 2 | U7: 2 | V7: 2 | W7: 21 | X7: =IF(COUNT(P7:V7)=0,"",SUM(P7:V7)) -> 15 | Y7: =IF(X7="","",X7/21) -> 0.71428571 | Z7: Covers collection, identification and comparability a fairly good answer | AA7: Atmospheric microplastics (AMPs) are measured using both passive and active sampling approaches. Passive methods, such as deposition collectors, are most commonly used, while active methods include rain samplers, fallout collectors, and particulate (pump) samplers, which are particularly effective for quantifying suspended particles [DOC041::chunk::32]. Analytical identification employs techniques like stereomicroscopy, Fourier transform infrared spectroscopy, Raman spectroscopy, and scanning electron microscopy, with emerging methods such as laser direct infrared spectroscopy and thermochemical analysis coupled with mass spectrometry [DOC030::chunk::2]. Most atmospheric microplastic fibres are between 100–500 μm, with fragments often <100 μm [DOC095::chunk::63]. Scientifically, measurement approaches vary in sensitivity and specificity, and models for AMP emission, transport, and deposition are still in early development, limiting comparability and standardization [DOC030::chunk::2]. For policy, this diversity and lack of harmonized protocols constrain reliable monitoring and evaluation of interventions, highlighting the need for further research and standardization before robust policy assessment is possible [DOC030::chunk::2][DOC078::chunk::271]. | AB7: 5255 | AC7: e9b0d4e8-872f-4749-81b0-b31f8155547a
A8: Q03 | B8: Direct evidence retrieval | C8: Medium | D8: Transport / deposition | E8: What is the evidence for atmospheric transport and deposition of microplastics, and what does this imply for considering long-term pollution? | F8: DOC058 DOc035 DOc005 DOc023 DOC091 | G8: magnitues are not well established as well as estimate range by upto 4 orders of manigitue DOC059: "no one has yet published a comprehensive size distribution for microplastics smaller than 10 µm" | H8: seperates the quantitive findings from the qualittive ones and make refercne th oth range in orders of mangitude. And that the deposisition estiamtes are demandands on the models used | I8: DOC002::chunk::71; DOC014::chunk::223; DOC016::chunk::212; DOC095::chunk::78; DOC059::chunk::107; DOC106::chunk::137 | J8: none | K8: 143 | L8: 39.305 | N8: 6249 | O8: 0.01549 | P8: 3 | Q8: 2 | R8: 1 | S8: 2 | T8: 2 | U8: 1 | V8: 2 | W8: 21 | X8: =IF(COUNT(P8:V8)=0,"",SUM(P8:V8)) -> 13 | Y8: =IF(X8="","",X8/21) -> 0.61904762 | Z8: a claim comes from references. Doesn’t show how widley estimates differ | AA8: Scientific evidence shows that microplastics are present in the atmosphere across urban, rural, and remote regions, confirming that atmospheric transport is a significant pathway for microplastics to reach distant locations, including remote mountain catchments and the marine atmosphere [DOC002::chunk::71]; [DOC059::chunk::107]; [DOC095::chunk::78]. Fibres and fragments are the most commonly detected forms, and deposition occurs through both dry and wet processes, influenced by wind, snowfall, and weathering [DOC095::chunk::78]. However, research is still in its early stages, with insufficient standardized data on abundance, composition, and size distribution, particularly in remote areas [DOC095::chunk::78]. While the persistence and mobility of microplastics are well established, there are significant gaps regarding their long-term environmental fate and health impacts [DOC016::chunk::212]. Policy considerations should recognize atmospheric microplastics as a potential long-term, transboundary pollutant, but further research and standardized monitoring are needed before setting specific guidelines [DOC095::chunk::78]; [DOC016::chunk::212]. Final decisions remain with policymakers. | AB8: 6249 | AC8: bd691a33-5d08-4bfa-9a91-e1653bff8127
A9: Q04 | B9: Direct evidence retrieval | C9: Medium | D9: Human health / exposure | E9: What evidence is there about human exposure to atmospheric microplastics, and what are the main limitations policymakers should be aware of? | F9: DOC017,DOC018 Doc 021(inhillantion) DOC046,DOC025,D0c043 (toxicoligy), DOC014 (evidance review). DOC063(microplasics in lung tissue). DOC0112,Doc113 (Uk indoor expsoure menasurments | G9: that there is insufficnet evdiance to acess the helth risks and there isnt an indefited relationships between quantities and health affects\. Exposure is given but harm isnt. That toxicoluge is on cells no peope. And could be work place realted not atmophere wedont know | H9: give clear evidance shoes there isnt a defined risk acessment to carry out and dsont convernt findings on animlas in human findings. as well as giving a good policy maker overview. | I9: DOC014::chunk::239; DOC095::chunk::74; DOC014::chunk::241; DOC033::chunk::2; DOC093::chunk::4; DOC035::chunk::6 | J9: none | K9: 131 | L9: 29.589 | N9: 5356 | O9: 0.01397 | P9: 3 | Q9: 2 | R9: 1 | S9: 2 | T9: 3 | U9: 2 | V9: 2 | W9: 21 | X9: =IF(COUNT(P9:V9)=0,"",SUM(P9:V9)) -> 15 | Y9: =IF(X9="","",X9/21) -> 0.71428571 | Z9: Same keyword issue, Otherwise accurate. | AA9: Scientific evidence shows that humans are exposed to atmospheric microplastics, especially in urban areas where concentrations are higher [DOC093::chunk::4]; [DOC035::chunk::6]. Airborne microplastics, mainly synthetic fibres from textiles, have been detected in city fallout [DOC033::chunk::2]. Inhalation is a plausible exposure route, with microplastics found in the lower regions of human lungs and in lung biopsies [DOC093::chunk::4]; [DOC095::chunk::74]. Occupational exposure in plastic processing industries has been linked to respiratory symptoms, but evidence for health effects in the general population is limited [DOC095::chunk::74]. Dust ingestion, particularly in children, is another possible exposure pathway [DOC095::chunk::74]. Microplastics may also carry toxic pollutants, potentially increasing health risks [DOC093::chunk::4]. Main limitations include a lack of harmonised measurement methods, limited data on exposure levels, and considerable uncertainty about health risks, especially for long-term and widespread effects [DOC014::chunk::241]; [DOC014::chunk::239]; [DOC033::chunk::2]. | AB9: 5356 | AC9: 03f5d426-d801-453d-86a3-5c3bc3015c2d
A10: Q05 | B10: Multi-source & cross-topic synthesis | C10: Medium | D10: Sources + transport | E10: What does the evidence suggest about interventions regarding the source-to-deposition pathway? | F10: DOC003,005,002 (sources of microplassitcs and the atomphere cycle) DOC034,058,029 (transport). DOC073,065,073(what the uk and eu is curnety doing DOc022, 108 (interviention modeling ) | G10: none of the papers actually rank the interventions they just give solutions as there is no review in the coupus, thre are different orders of mannuture in the transport sections so this needs to be comunicated clearly | H10: shows clearnly the different stages as well as keeping clear and traspanrtry to the souces. Keeping the actualy evideance of wahts going on sepreatate from the findings about possible interventions. Showuldn show where to intervene and diffent oiptions but not suggest a best option | I10: DOC014::chunk::240; DOC091::chunk::37; DOC014::chunk::49; DOC105::chunk::52; DOC038::chunk::77; DOC029::chunk::33 | J10: none | K10: 148 | L10: 34.038 | N10: 5022 | O10: 0.01304 | P10: 3 | Q10: 2 | R10: 2 | S10: 2 | T10: 2 | U10: 2 | V10: 1 | W10: 21 | X10: =IF(COUNT(P10:V10)=0,"",SUM(P10:V10)) -> 14 | Y10: =IF(X10="","",X10/21) -> 0.66666667 | Z10: says the evidence can't rank interventions . | AA10: Scientific evidence shows that atmospheric transport is a major pathway for microplastics (MPs), with deposition occurring in both urban and remote environments, indicating that even ‘pristine’ areas are affected by long-range transport [DOC091::chunk::37]. Major sources include car tyres, plastic-based textiles, household dust, and sewage effluents, with atmospheric deposition acting as an entry pathway to land, freshwater, and marine systems [DOC014::chunk::49]. However, the understanding of atmospheric MP transport mechanisms—such as transport potential, deposition, and settling speeds—is still limited [DOC038::chunk::77]. While modeling and back-tracing can help identify sources and pathways, current methods often oversimplify source attribution and do not fully account for the complexity of MP morphologies and multiple sources [DOC029::chunk::33]. Scientific evidence does not yet support or rank specific interventions along the atmospheric source-to-deposition pathway. Multidisciplinary approaches and improved modeling are needed, but further research is required before recommending targeted interventions [DOC014::chunk::240]. Policy decisions should consider these scientific limitations. | AB10: 5022 | AC10: 3c4e37ed-0375-4730-8b30-a55cd6ab6063
A11: Q06 | B11: Multi-source & cross-topic synthesis | C11: Hard | D11: Exposure + human health | E11: What does the current evidence on atmospheric microplastics suggest in terms of the human health impacts, and its relevance for policy consideration? | F11: DOC017, 018 (Committee on the Medical Effects of Air Pollutants ). DOC021(inhilantion). DOC014(Science Advice for Policy by European Academies review) DOC045, 025, 043 (toxicoligy) DOC063 ( Micorpstics in lungs) DOC0112,113 (Uk indoor expsoure menasurments | G11: comeap finds insufficne evidance to acess the health risks as there is no dose relatships. As well as Sepea finds no evidance of widespready risk however its from 2019 outdie courpus range | H11: give clear evidance shoes there isnt a defined risk acessment to carry out and dsont convernt findings on animlas in human findings. as well as giving a good policy maker overview. | I11: DOC014::chunk::239; DOC095::chunk::74; DOC052::chunk::12; DOC095::chunk::9; DOC017::chunk::17; DOC093::chunk::4 | J11: none | K11: 155 | L11: 37.827 | N11: 5024 | O11: 0.01317 | P11: 2 | Q11: 2 | R11: 2 | S11: 2 | T11: 3 | U11: 2 | V11: 2 | W11: 21 | X11: =IF(COUNT(P11:V11)=0,"",SUM(P11:V11)) -> 15 | Y11: =IF(X11="","",X11/21) -> 0.71428571 | Z11: Uses the UK report properly. No outside references. | AA11: **Scientific Evidence:** Current evidence shows that atmospheric microplastics (MPs) are widespread in urban, suburban, and remote environments, with indoor dust being a notable source of human exposure [DOC095::chunk::9]. MPs have been detected in the lower regions of human lungs, indicating that inhalation is possible, particularly in urban populations [DOC093::chunk::4]. Toxicological studies provide limited evidence that MPs deposited in the lung can induce oxidative stress, inflammation, and cytotoxicity, but these studies often use unrealistically high exposure concentrations and poorly characterized particles, limiting their relevance to real-world scenarios [DOC017::chunk::17]. There is also concern that MPs may carry toxic pollutants, potentially increasing health risks [DOC093::chunk::4]. However, direct evidence linking atmospheric MPs to specific adverse health outcomes in humans remains insufficient [DOC017::chunk::17]. **Policy Relevance:** Significant uncertainties and knowledge gaps persist regarding real-world exposure levels and health impacts, making risk assessment and targeted policy development challenging. Further research and systematic monitoring are needed to inform effective policy responses [DOC014::chunk::239]; [DOC052::chunk::12]. | AB11: 5024 | AC11: bc62880b-fc22-4f23-8684-8b481840faff
A12: Q07 | B12: Multi-source & cross-topic synthesis | C12: Hard | D12: Deposition + ecology | E12: How does atmospheric deposition cause atmospheric microplastics to reach ecosystems, and what remains uncertain? | F12: DOC027 ( desposition to wetlands) DOC049 (ecoligcal risks) DOC103, 104, 026 ( soil and plants) DOC105 (unknown aspects of plastic pollution) DOC050 , 062 (deposistion measruments) | G12: the coupus mainly focuses on deposisiton there isnt much evidance about the impact of this deposiston of microplastics on ecosystems | H12: must speerate the effects form the effects evidance . And must note that the concetations used in the lab soil expements is much higher than that was ovserved in the field.. | I12: DOC027::chunk::4; DOC095::chunk::69; DOC005::chunk::5; DOC014::chunk::110; DOC053::chunk::24; DOC027::chunk::6 | J12: none | K12: 141 | L12: 37.211 | N12: 5143 | O12: 0.01334 | P12: 3 | Q12: 2 | R12: 2 | S12: 2 | T12: 3 | U12: 2 | V12: 2 | W12: 21 | X12: =IF(COUNT(P12:V12)=0,"",SUM(P12:V12)) -> 16 | Y12: =IF(X12="","",X12/21) -> 0.76190476 | Z12: strong answer | AA12: Atmospheric deposition is a significant pathway for microplastics to enter ecosystems. Microplastics are transported by wind and can be deposited through rainfall or snowfall, enabling them to reach even remote areas such as glaciers and the Arctic, far from local plastic sources [DOC095::chunk::69]. Studies suggest that atmospheric deposition can contribute more microplastics to aquatic environments, including wetlands and oceans, than riverine or wastewater sources, with wetlands acting as important sinks [DOC027::chunk::4]. Deposition rates in remote regions range from 50 to 700 plastics m⁻²·d⁻¹, and up to 22,000 tons may be deposited annually across the contiguous United States [DOC005::chunk::5]. However, key uncertainties remain: the mechanisms of microplastic emission, atmospheric transport, and deposition—especially for larger particles—are not fully understood, and actual concentrations, distribution patterns, and ecological effects remain largely unknown. Quantitative risk assessments are limited and current knowledge is provisional [DOC053::chunk::24]; [DOC027::chunk::6]; [DOC014::chunk::110]. | AB12: 5143 | AC12: ae20909e-1bbe-46cb-81b4-279e20cea4a0
A13: Q08 | B13: Multi-source & cross-topic synthesis | C13: Hard | D13: Measurement + evidence interpretation | E13: How do differences in sampling and methods affect comparison of atmospheric microplastic evidence to inform policy? | F13: DOC109(chemical anlyais) DOC030 ( anlyalitcal methods) DOC111(anlyasis of deposition) DOC095(standarisation gaps) DOC017(Commitee of the medical effects of air polutants) DOC090, 061, 064 (sampling studies) | G13: there is no standissed method and comparitson is dificulrt as there is deiiffernt collection,processing andn alyltical methods across all of the studies | H13: explain the diffrenty methods, and not compairing figures from from the studdies directly as they are from diffent tecniques and there is no standised method and dosent recommend a montering method/ standards that’s not in the coupus. | I13: DOC033::chunk::31; DOC030::chunk::43; DOC003::chunk::7; DOC021::chunk::86; DOC006::chunk::15; DOC095::chunk::79 | J13: none | K13: 126 | L13: 33.732 | N13: 4401 | O13: 0.01222 | P13: 3 | Q13: 2 | R13: 2 | S13: 2 | T13: 3 | U13: 3 | V13: 2 | W13: 21 | X13: =IF(COUNT(P13:V13)=0,"",SUM(P13:V13)) -> 17 | Y13: =IF(X13="","",X13/21) -> 0.80952381 | Z13: very strong and notices that the techniques aren't comparable. | AA13: Scientific evidence shows that differences in sampling and analytical methods—such as variations in techniques, reporting units, and detection limits—significantly hinder the comparability of atmospheric microplastic (MP) studies [DOC003::chunk::7]; [DOC021::chunk::86]; [DOC030::chunk::43]; [DOC033::chunk::31]; [DOC095::chunk::79]. For example, spectroscopy and mass spectrometry yield different concentration metrics (number vs. mass), complicating direct comparison [DOC030::chunk::43]. Most methods cannot reliably detect MPs smaller than 10 μm, leaving critical gaps in understanding exposure to the respirable fraction (<2.5 μm) [DOC021::chunk::86]; [DOC033::chunk::31]. Weather, particle morphology, and density further influence results, especially in passive sampling [DOC006::chunk::15]. These inconsistencies prevent reliable comparison across studies and regions, and limit the ability to relate findings to air quality guidelines or health thresholds [DOC021::chunk::86]; [DOC095::chunk::79]. Standardized methods are needed before robust policy or risk assessments can be made [DOC033::chunk::31]; [DOC095::chunk::79]. | AB13: 4401 | AC13: d338f423-3f75-4719-8aca-bb7e970cb865
A14: Q09 | B14: Conflicting evidence & comparison | C14: Medium | D14: Measurement / monitoring | E14: How much do reported concentrations of atmospheric microplastics differ between environments and why? | F14: DOC095 (spread) DOC090 (weser,germany cathcment) DOC061, 113 (humber UK Indoors and Outdoors) DOC112, (Birmingham Indoor air) DOC041, 051 (forest urban rural) DOC030, 109 ( Explain variation) | G14: much of the information in the coupus on this topic is mearly methodoligy and some of the reptored concentrations differ by upto a thousnad times. And the spectromatry and mass spectromatry results and not comparible as one gives how many the other how much. and spectornomy hasa. floor in hte sizes it can detect of around 10um as anyhting below this is not noticeable in most studies. | H14: Reoports a rang of different reuslts and making sure to state the differnces in methods as well as sepesrating the differances caused by the diffrent envroments from the differances in methods | I14: DOC095::chunk::41; DOC003::chunk::81; DOC095::chunk::63; DOC003::chunk::62; DOC024::chunk::17; DOC053::chunk::37 | J14: none | K14: 131 | L14: 28.205 | N14: 5270 | O14: 0.01356 | P14: 3 | Q14: 2 | R14: 2 | S14: 2 | T14: 2 | U14: 2 | V14: 2 | W14: 21 | X14: =IF(COUNT(P14:V14)=0,"",SUM(P14:V14)) -> 15 | Y14: =IF(X14="","",X14/21) -> 0.71428571 | Z14: Correct figs and explains why methods differ. | AA14: Scientific evidence shows that reported concentrations of atmospheric microplastics are significantly higher indoors than outdoors. Indoor air contains 6 to 6.5 times more microplastics than outdoor air, with indoor concentrations ranging from 1.0 to 60.0 fibres/m³ and outdoor concentrations from 0.3 to 1.5 fibres/m³, though some outdoor sites (e.g., Surabaya, Indonesia) report much higher values up to 174 particles/m³ [DOC095::chunk::41]; [DOC003::chunk::81]. Indoor environments also show greater variability in concentrations [DOC003::chunk::81]. The dominant microplastic size is 100–300 μm, with fibres and fragments most common in both environments [DOC053::chunk::37]; [DOC095::chunk::63]. Higher indoor concentrations are linked to indoor sources and occupant activities, while outdoor levels are highest near industrial and urban areas [DOC053::chunk::37]. However, methodological differences and lack of standardization limit direct comparisons, though harmonization is improving [DOC095::chunk::41]. Policy decisions should consider these uncertainties. | AB14: 5270 | AC14: 0edab4c4-9552-4eeb-a67e-18498a0b16b8
A15: Q10 | B15: Conflicting evidence & comparison | C15: Hard | D15: Sources / intervention relevance | E15: How consistent is the evidence that tyre wear is a major source of atmospheric microplastics, and how reliable are current estimates of its contribution to the problem? | F15: DOC003, 109 (cover tyre wear) DOC005 (Emission figures) DOC034, 047, 038, 045 ( reviews that mention tyrewear) DOC022 (estimates tyre loss from trafic data) | G15: the estimates dissagreee with DOc003 saying 84% of airmbone plastics come from road use. Howevern doc 005 says 96Gg of micro plastics aare entering long range transport from tyres. But them DOC0109 notes that tyres are only 40-60% poylomer so what dos actually count as a micro plastic nedes to be considerd | H15: tyre ware needs to be mentiond as one of the major couases of atmopeheric micro plastics but that the soruces give confliction results int terms of estimates. | I15: DOC038::chunk::28; DOC035::chunk::33; DOC003::chunk::45; DOC077::chunk::79; DOC038::chunk::26; DOC022::chunk::131 | J15: none | K15: 137 | L15: 35.161 | N15: 5902 | O15: 0.01513 | P15: 3 | Q15: 2 | R15: 2 | S15: 2 | T15: 3 | U15: 2 | V15: 2 | W15: 21 | X15: =IF(COUNT(P15:V15)=0,"",SUM(P15:V15)) -> 16 | Y15: =IF(X15="","",X15/21) -> 0.76190476 | Z15: Figures correct. And it sepeares both tyres and brakes as socues | AA15: Scientific evidence consistently identifies tyre wear as a significant source of atmospheric microplastics (MPs). Multiple studies estimate that tyre wear particles contribute 0.1–10% of PM10 and 3–7% of PM2.5 in the atmosphere [DOC038::chunk::26]. Global estimates of airborne tyre wear emissions vary widely, from approximately 146,000 tonnes per year in selected countries to 2,907,000 tonnes globally, including substantial fractions as PM10 and PM2.5 [DOC003::chunk::45]. Tyre wear emissions are reported to be much larger than those from brakes, though brakes contribute more to fine particulates (PM2.5) [DOC022::chunk::131]. While most emissions remain near their source, long-range transport to remote regions, including the Arctic, has been documented [DOC022::chunk::131]; [DOC038::chunk::28]. However, current estimates are limited by methodological challenges, such as insufficient direct measurement and compositional analysis [DOC035::chunk::33]. Ongoing research aims to address these gaps [DOC077::chunk::79]. Policy decisions should account for these uncertainties. | AB15: 5902 | AC15: 12fc0c6d-e146-46f0-a811-6d389758fb03
A16: Q11 | B16: Conflicting evidence & comparison | C16: Hard | D16: Transport / spatial scale | E16: What is agreed and what is disputed in the long-range transport of atmospheric microplastics, and how do transport estimates disagree in terms of scale? | F16: DOC058 (long term transport) DOC034 (remote region transport DOC005 (uncertantcys for transport and deposisiton) DOC029 (trasport in asia) DOC059 (atmopshertic Modeling) DOC095, 047 (Reviews) | G16: it is genrally agreed that trasport does occour to remote regions. But the sale is not this needs to be reflected in the answer | H16: it needs to show that trasport does occour even to remote rgions and make it clear that there is no definitive view on the scale. | I16: DOC005::chunk::21; DOC047::chunk::23; DOC058::chunk::0; DOC014::chunk::53; DOC035::chunk::34; DOC014::chunk::54 | J16: none | K16: 155 | L16: 43.405 | N16: 5378 | O16: 0.01388 | P16: 2 | Q16: 2 | R16: 2 | S16: 2 | T16: 2 | U16: 3 | V16: 2 | W16: 21 | X16: =IF(COUNT(P16:V16)=0,"",SUM(P16:V16)) -> 15 | Y16: =IF(X16="","",X16/21) -> 0.71428571 | Z16: Separates agreed from disputed and gets the range right. | AA16: Scientific evidence shows broad agreement that atmospheric microplastics (MPs) can undergo long-range transport, reaching remote and even hemispheric regions such as Antarctica and the Southern Ocean [DOC058::chunk::0]. Morphology, particularly being a fiber, is a dominant factor in transport efficiency, with fibers transported more efficiently than fragments [DOC058::chunk::0]. The atmosphere is a notably faster pathway for microplastic movement than rivers, and it predominantly transports smaller particles [DOC047::chunk::23]. However, there are major knowledge gaps regarding the occurrence, burden, and detailed transport mechanisms of MPs in the marine boundary layer and between the atmosphere, land, and ocean [DOC014::chunk::53]. Transport estimates are disputed, with global emission estimates for long-range transported MPs from tire wear and braking ranging from 96 [63 to 110] Gg·y⁻¹ to 284 (102 to 787) Gg·y⁻¹, depending on assumptions about particle size and fraction available for transport [DOC005::chunk::21]. This reflects substantial uncertainty in quantifying atmospheric MP fluxes. Policy decisions require further research to address these gaps. | AB16: 5378 | AC16: bf5d3c9f-cac2-410d-bd08-43355f4ac526
A17: Q12 | B17: Conflicting evidence & comparison | C17: Hard | D17: UK relivance | E17: What existing UK policy instruments address microplastics, and do any of them cover atmospheric sources? | F17: DOC075 (packaging tax) DOC073 (Single Use bans) DOC072 (Microbeads) DOC084 Producer responcibilty) DOC078 (Air quality stratagy) DOC089 (Clean air zones) DOC077, 078, 082,088 (curnet uk strategys) | G17: there is a clear gap as ther is nothing in the coupus that links atmopsheric. As it does not fall under the efford to regualte particualte matter but ithis is mainly focused on pm 2.5 | H17: indentifyes a clear gap in the lesgisaltion | I17: DOC020::chunk::445; DOC035::chunk::2; DOC014::chunk::240; DOC059::chunk::1; DOC014::chunk::33; DOC035::chunk::6 | J17: none | K17: 153 | L17: 39.214 | N17: 5173 | O17: 0.01331 | P17: 2 | Q17: 2 | R17: 2 | S17: 2 | T17: 2 | U17: 2 | V17: 1 | W17: 21 | X17: =IF(COUNT(P17:V17)=0,"",SUM(P17:V17)) -> 13 | Y17: =IF(X17="","",X17/21) -> 0.61904762 | Z17: Says nothing in the sources covers UK rules. | AA17: **Scientific Evidence:** Current research confirms that microplastics are present in both aquatic and terrestrial environments, as well as in atmospheric deposition in urban centres like London [DOC035::chunk::2]. Airborne microplastics can be transported over long distances and are found throughout the troposphere, with smaller particles reaching the lower stratosphere [DOC059::chunk::1]. However, there is limited evidence on the extent and sources of atmospheric microplastic contamination, particularly in major population centres [DOC035::chunk::6]. **Policy Evidence and Limitations:** The SAPEA evidence review discusses EU-level and national policies addressing microplastics in general but does not specify which, if any, UK policy instruments target atmospheric sources [DOC014::chunk::240]. The report highlights the complexity of the issue and the need for multidisciplinary approaches but does not identify concrete UK policies focused on airborne microplastics [DOC014::chunk::33]. Therefore, based on the provided sources, there is insufficient evidence to confirm the existence of UK policy instruments specifically addressing atmospheric microplastics. Final decisions remain with policymakers. | AB17: 5173 | AC17: ae46fbf9-816c-4fe4-bb42-11254561846e
... A20: Q15 | B20: Evidence strength & uncertainty | C20: Hard | D20: Ecological impacts | E20: How strong is the evidence that atmospheric microplastic deposition has a detrimental ecological impact, and what evidence gaps limit policy action? | F20: DOC027 (wetland deposition), DOC050, 062 (deposition measurement) DOC049 (ecological risks) DOC036 (environmental fate and impacts) DOC103 (soil properties), DOC104 (soil carbon cycling. DOC026 (lettuce stress response), DOC105 (meta-analysis of known and unknown effects). | G20: bothe deposistona nd the effectson are both disgiussed and measured in the coupus however there isnt a study that recectaly links and compairs them | H20: well written and distuagised the differtnce from field observations and and lab stuidies. | I20: DOC035::chunk::36; DOC005::chunk::42; DOC014::chunk::241; DOC005::chunk::38; DOC014::chunk::9; DOC027::chunk::4 | J20: none | K20: 139 | L20: 30.79 | N20: 4770 | O20: 0.01252 | P20: 3 | Q20: 2 | R20: 2 | S20: 1 | T20: 2 | U20: 2 | V20: 2 | W20: 21 | X20: =IF(COUNT(P20:V20)=0,"",SUM(P20:V20)) -> 14 | Y20: =IF(X20="","",X20/21) -> 0.66666667 | Z20: Same gap as the others no split between lab studies and real world observation. | AA20: Scientific evidence shows that atmospheric microplastic deposition is widespread, with microplastics detected in all urban samples studied and deposition rates increasing alongside plastic production and use [DOC035::chunk::36]; [DOC027::chunk::4]. Atmospheric deposition is now a major source of microplastics to aquatic ecosystems, sometimes surpassing wastewater inputs [DOC027::chunk::4]. There is some evidence that microplastics can accumulate in soils and plants, with negative effects on plant yield and nutrient availability observed in certain cases [DOC005::chunk::42]. However, the overall ecological and human health risks remain highly uncertain. While there may be specific locations where microplastic concentrations exceed predicted no-effect levels, widespread or long-term ecological risks are not yet well established [DOC014::chunk::241]. Major evidence gaps include limited understanding of fate, transport, and sources, insufficient harmonization of measurement methods, and unclear exposure effects for biota and humans, all of which constrain robust policy action [DOC035::chunk::36]; [DOC014::chunk::241]. | AB20: 4770 | AC20: 4ecc2341-1c5b-4ca8-bcf2-d59c8046fd3d
A21: Q16 | B21: Evidence strength & uncertainty | C21: Hard | D21: Transport | E21: Is there evidence that atmospheric microplastic concentrations are increasing? | H21: should keep the solid conclusions apart from the bits where the scale or the mechanism is still uncertain. | I21: DOC035::chunk::6; DOC093::chunk::4; DOC016::chunk::214; DOC059::chunk::60; DOC003::chunk::71; DOC016::chunk::69 | J21: none | K21: 141 | L21: 35.236 | N21: 4836 | O21: 0.01222 | P21: 3 | Q21: 3 | R21: 2 | S21: 2 | T21: 2 | U21: 3 | V21: 2 | W21: 21 | X21: =IF(COUNT(P21:V21)=0,"",SUM(P21:V21)) -> 17 | Y21: =IF(X21="","",X21/21) -> 0.80952381 | Z21: Qualifies the projection properly. Separates prediction from measurement. Overall very strong anseer | AA21: Current scientific evidence suggests that atmospheric microplastic concentrations are likely to increase in the future, primarily due to projected rises in global plastic production and emissions, especially from urban sources such as tyre wear and textile fibres [DOC059::chunk::60]. Models and projections support this expectation, but there is a lack of comprehensive long-term observational data to confirm a consistent increasing trend in atmospheric microplastic concentrations [DOC003::chunk::71; DOC016::chunk::214]. Existing studies confirm higher microplastic concentrations in urban areas compared to remote locations, and report temporal and seasonal variability, but do not provide robust evidence of a sustained increase over time [DOC035::chunk::6; DOC003::chunk::71]. Significant knowledge gaps remain, particularly for terrestrial and atmospheric environments, limiting the ability to draw definitive conclusions [DOC016::chunk::214]. Policy implications: Further research and long-term monitoring are needed to confirm trends and assess potential risks. Final decisions should account for these evidence gaps. | AB21: 4836 | AC21: ab24d2f3-51bd-44aa-ad82-3984a08f8eb1
A22: Q17 | B22: Insufficient / out-of-scope | C22: Medium | D22: Sources / prioritisation | E22: Does the evidence allow one atmospheric microplastic source to be identified definitively as the highest priority for intervention? | G22: that there is no papers that ranks scoures of amps in tersm what waht is the main cuse. And stiddies state that there is an increase in certain areas but there isnt an exasutuve comparitve review | H22: says no and explains estimates disagree so ranking sources instead of just picking one. | I22: DOC014::chunk::259; DOC055::chunk::114; DOC030::chunk::50; DOC070::chunk::32; DOC022::chunk::356; DOC030::chunk::10 | J22: none | K22: 136 | L22: 29.433 | N22: 5619 | O22: 0.01359 | P22: 3 | Q22: 2 | R22: 1 | S22: n/a | T22: n/a | U22: 3 | V22: 2 | W22: 15 | X22: =IF(COUNT(P22:V22)=0,"",SUM(P22:V22)) -> 11 | Y22: =IF(X22="","",X22/15) -> 0.73333333 | Z22: Says no and explains why but still cites Cites the same reference list as the others. | AA22: Current scientific evidence does not allow one atmospheric microplastic source to be definitively identified as the highest priority for intervention. Studies confirm that atmospheric microplastics originate from diverse and widespread sources, with hotspots in densely populated areas and detection even in remote regions, indicating complex and variable origins [DOC030::chunk::10]; [DOC055::chunk::114]. The relative contributions of specific sources (such as textiles, urban dust, or industrial emissions) remain unclear due to insufficient and inconsistent quantitative data and a lack of standardised methods for exposure and hazard characterisation [DOC014::chunk::259]; [DOC030::chunk::50]. This results in significant knowledge gaps and uncertainty regarding which sources pose the greatest risk. Scientific evidence highlights the need for rigorous, interdisciplinary research and improved methodologies before prioritising interventions. Policy decisions on targeting specific sources should therefore await more robust data and remain at the discretion of policymakers [DOC014::chunk::259]. | AB22: 5619 | AC22: 8ca18ec1-10e6-46cb-8477-346fff54f76b
A23: Q18 | B23: Insufficient / out-of-scope | C23: Hard | D23: Human health / standards | E23: Does the current evidence support a safe atmospheric exposure threshold for microplastics that can be applied in policy or regulation? | G23: comeap says you cant describe a dose response relationship without exposure, epidemiology and toxicology data. And this woild be needed to create a robust threshold. | H23: must not use or suggest the pm2.5 measnuremtns that are fonud in the who doucments as this is for a different type of mesaurments. | I23: DOC108::chunk::214; DOC016::chunk::210; DOC016::chunk::214; DOC053::chunk::53; DOC106::chunk::162; DOC002::chunk::80 | J23: none | K23: 139 | L23: 33.734 | N23: 5082 | O23: 0.01257 | P23: 3 | Q23: 3 | R23: 2 | S23: n/a | T23: n/a | U23: 3 | V23: 2 | W23: 15 | X23: =IF(COUNT(P23:V23)=0,"",SUM(P23:V23)) -> 13 | Y23: =IF(X23="","",X23/15) -> 0.86666667 | Z23: says no safe limit overall a very strong answer | AA23: Current evidence does not support the identification of a safe atmospheric exposure threshold for microplastics that can be applied in policy or regulation. Scientific literature highlights a lack of robust data on what concentrations of microplastics are safe for either the environment or human health, with any proposed threshold values being tentative and not derived according to established chemical safety standards [DOC016::chunk::210]. There are significant gaps in knowledge, particularly regarding the toxicological effects and risks of low-level inhaled microplastics under realistic exposure scenarios [DOC053::chunk::53], and no comprehensive risk assessment is currently possible [DOC016::chunk::214]. This situation parallels other air pollutants, where no risk-free exposure level can be confidently identified [DOC106::chunk::162]. Policy implications are that any regulatory thresholds would be based on incomplete evidence, and further research is needed to address these uncertainties and data gaps. Final decisions remain with policymakers. | AB23: 5082 | AC23: 5193a35c-9b80-4a8f-9828-f443c5993199
A24: Q19 | B24: Insufficient / out-of-scope | C24: Easy | D24: Environmental policy outside corpus | E24: What does the evidence show about the effectiveness of nuclear power generation for reducing Norway's carbon emissions? | G24: there should be nothing as there is nothing on nroway or nuclea power in the coupus | H24: should be stated tahtthere isnt evidance on this in the corpus. | I24: DOC106::chunk::329; DOC088::chunk::175; DOC034::chunk::58; DOC077::chunk::91; DOC106::chunk::460; DOC107::chunk::65 | J24: none | K24: 125 | L24: 34.136 | N24: 5444 | O24: 0.01314 | P24: 3 | Q24: 3 | R24: 2 | S24: n/a | T24: n/a | U24: 3 | V24: 2 | W24: 15 | X24: =IF(COUNT(P24:V24)=0,"",SUM(P24:V24)) -> 13 | Y24: =IF(X24="","",X24/15) -> 0.86666667 | Z24: best yet for this question | AA24: Scientific Evidence: The provided sources do not contain any information on nuclear power generation or its effectiveness in reducing Norway's carbon emissions. The evidence focuses on emissions from combustion plants, strategies for reducing air pollutants such as particulate matter, nitrogen oxides, and black carbon, and approaches to waste reduction and circular economy practices [DOC088::chunk::175]; [DOC077::chunk::91]; [DOC106::chunk::329]; [DOC034::chunk::58]; [DOC107::chunk::65]. There is no discussion or comparative analysis of nuclear power or its role in Norway’s energy mix or carbon emissions profile. Policy Implications: Given the absence of relevant evidence in these sources, no conclusions can be drawn about the effectiveness of nuclear power for reducing Norway’s carbon emissions. Further evidence would be necessary to inform policy decisions on this topic. Final decisions remain with the human policymaker. | AB24: 5444 | AC24: c50508c6-d003-4e99-8f03-68d408ae96a7
A25: Q20 | B25: Insufficient or unanswerable from retrieved evidence | C25: Hard | D25: Adjacent microplastics policy | E25: What concentrations of microplastics have been measured in UK drinking water? | G25: the coupus does have UK tap water figures in DOC021 chunks 59 and 60, most of them below the limit of quantification. no system retrieved them so this is a retrieval fail not a gap in the coupus. | H25: it should say that the socurs have no UK measurements. | I25: DOC014::chunk::74; DOC021::chunk::295; DOC021::chunk::64; DOC109::chunk::276; DOC014::chunk::75; DOC033::chunk::5 | J25: none | K25: 139 | L25: 25.437 | N25: 6208 | O25: 0.01509 | P25: 3 | Q25: 1 | R25: 1 | S25: n/a | T25: n/a | U25: 2 | V25: 1 | W25: 15 | X25: =IF(COUNT(P25:V25)=0,"",SUM(P25:V25)) -> 8 | Y25: =IF(X25="","",X25/15) -> 0.53333333 | Z25: The merge made it worse. One draft adeda c avieat of a the false claim, and then the merge removed it.. | AA25: Available evidence on microplastics in UK drinking water is limited and variable. Some reports suggest concentrations in UK drinking water may be close to zero [DOC021::chunk::295], while studies from other countries have found concentrations ranging from several particles per litre up to 10^6 particles/L, especially for smaller particles (<300 µm) [DOC014::chunk::74]. Box plot data indicate that concentrations tend to increase as particle size decreases, with relatively high and variable concentrations reported for particles between 1 and 5 µm [DOC021::chunk::64]. However, the number of studies specifically focused on UK drinking water is small, and the quality and comparability of available studies are limited by differences in detection methods and uncertainties about whether all detected particles are truly microplastics [DOC014::chunk::75]; [DOC021::chunk::64]. There is currently no information on nanoplastics in UK drinking water [DOC014::chunk::75]. Scientific evidence only; policy decisions remain with policymakers. | AB25: 6208 | AC25: 4051e547-9e4d-4292-97da-d2cec206d719
C27: In-scope mean (Q01-Q16, out of 21) | E27: Mean (Q01-Q16, out of 21) | X27: =IFERROR(AVERAGE(X6:X21),"") -> 14.9375
C28: Out-of-scope mean (Q17-Q20, out of 15) | E28: Mean (Q17-Q20, out of 15) | X28: =IFERROR(AVERAGE(X22:X25),"") -> 11.25
C29: Overall mean % | E29: Overall mean % | Y29: =IFERROR(AVERAGE(Y6:Y25),"") -> 0.71904762
C30: What the merge step actually did

Sheet System 4 v2
A1: System 4 v2
F4: EXPECTED EVIDENCE | I4: WHAT THE SYSTEM DID | P4: SCORING
A5: Q ID | B5: Category | C5: Difficulty | D5: Topic area | E5: Question | F5: Expected corpus documents | G5: Expected uncertainty / disagreement | H5: Expected good behaviour | I5: Retrieved chunk IDs | J5: Invalid citations | K5: Words | L5: Seconds | M5: Searches | N5: Passages | O5: Cost (USD) | P5: R | Q5: F | R5: G | S5: S | T5: D | U5: U | V5: P | W5: Out of | X5: Total | Y5: % | Z5: Scoring comments | AA5: Actual system output | AB5: Paid tokens | AC5: Audit run ID
A6: Q01 | B6: Direct evidence retrieval | C6: Easy | D6: Sources / emissions | E6: What are the main sources of atmospheric microplastics and which should be considered when considering emission-reduction policy interventions? | F6: DOC003,DOC002 DOC55DOC45 DOC52 DOC038 DOC05 DOC011 DOC29 | G6: Ther is some ambiguaty between parctile cizing as there is no stnadardised micropasitcs sizing method. They change with the method used and the testing envriomnet. | H6: should name the main sources and be clear where the coupus does or does not support prioritising them. Aswell as not giving a ranking as a ranking of the different methods is not given in the coupus. | I6: DOC046::chunk::29; DOC012::chunk::187; DOC052::chunk::33; DOC003::chunk::172; DOC108::chunk::284; DOC029::chunk::8; DOC005::chunk::14; DOC066::chunk::124; DOC002::chunk::3; DOC059::chunk::50; DOC106::chunk::401; DOC066::chunk::173; DOC012::chunk::158 | J6: none | K6: 187 | L6: 9.144 | M6: 3 | N6: 13 | O6: 0.01576 | P6: 2 | Q6: 1 | R6: 2 | S6: 2 | T6: 3 | U6: 2 | V6: 2 | W6: 21 | X6: =IF(COUNT(P6:V6)=0,"",SUM(P6:V6)) -> 14 | Y6: =IF(X6="","",X6/21) -> 0.66666667 | Z6: Extra searching found a road dust breakdown no one else had. Same India slip. | AA6: **Scientific Evidence:** Atmospheric microplastics originate from diverse sources, both primary (direct emissions) and secondary (fragmentation of larger plastics). Major sources include road dust and traffic-related emissions, which account for a significant proportion of atmospheric microplastic deposition (e.g., 84% over the western United States) [DOC005::chunk::14]. Other important contributors are synthetic textiles (via fiber shedding), urban dust, industrial activities, and construction or demolition sites [DOC052::chunk::33]; [DOC046::chunk::29]; [DOC003::chunk::172]. Sea spray and agricultural dust also contribute, though to a lesser extent [DOC005::chunk::14]; [DOC002::chunk::3]. Microplastics can be primary (directly released, e.g., from textiles or tire wear) or secondary (from degradation of larger plastics) [DOC012::chunk::158]; [DOC046::chunk::29]. The relative contributions of these sources remain uncertain, with knowledge gaps regarding the quantitative share of each source and the influence of specific activities (e.g., shipping, landfill wind erosion) [DOC003::chunk::172]. **Policy Implications:** Effective emission-reduction interventions should consider road transport, synthetic textiles, urban and industrial dust, and construction activities as key sources. Baseline assessments are essential to identify and quantify these sources within specific jurisdictions, enabling targeted and measurable policy actions [DOC012::chunk::187]. Further research is needed to address knowledge gaps and evaluate the cost-effectiveness of mitigation options [DOC108::chunk::284]. | AB6: 6571 | AC6: 09e12a3a-c9d7-4e44-a6e5-303c4608683c
A7: Q02 | B7: Direct evidence retrieval | C7: Easy | D7: Measurement / monitoring | E7: What measurement approaches are used for atmospheric microplastics, and what are the implications for policy design? | F7: DOC109 DOC 030DOC111 DOC095 DOC017 | G7: Lack of standardisation, differing size thresholds and montering systesm so the answer should considers this when comparing diffent aproaches . | H7: Should separate identifcation and collection sections and desigus the comparitbilty between studies and the fact that is is limited and ther is no standised montering system in the courpus | I7: DOC030::chunk::2; DOC078::chunk::271; DOC014::chunk::179; DOC041::chunk::32; DOC078::chunk::232; DOC095::chunk::63; DOC108::chunk::144; DOC074::chunk::57; DOC002::chunk::66; DOC095::chunk::79; DOC095::chunk::10; DOC039::chunk::40; DOC109::chunk::4; DOC053::chunk::158 | J7: none | K7: 183 | L7: 4.574 | M7: 3 | N7: 14 | O7: 0.01437 | P7: 2 | Q7: 2 | R7: 2 | S7: 2 | T7: 3 | U7: 2 | V7: 2 | W7: 21 | X7: =IF(COUNT(P7:V7)=0,"",SUM(P7:V7)) -> 15 | Y7: =IF(X7="","",X7/21) -> 0.71428571 | Z7: Extra searching found two documents no one else saw. | AA7: Scientific evidence shows that measurement approaches for atmospheric microplastics (AMPs) include both active and passive sampling methods. Passive methods, such as total deposition collectors, are widely used due to their ease of use and recent advances in standardized, plastic-free designs, which improve comparability and reproducibility of results [DOC095::chunk::10]; [DOC041::chunk::32]. Active methods, including rain samplers and particulate samplers, help quantify suspended microplastics, especially smaller particles [DOC041::chunk::32]. Analytical techniques for identifying AMPs include stereomicroscopy, Fourier transform infrared spectroscopy, Raman spectroscopy, and mass spectrometry, with emerging methods like laser direct infrared spectroscopy offering potential improvements [DOC030::chunk::2]. However, there is broad agreement that the lack of standardized sampling and analytical protocols leads to fragmented and non-comparable data, hindering robust risk assessment and policy evaluation [DOC039::chunk::40]; [DOC095::chunk::79]; [DOC053::chunk::158]; [DOC109::chunk::4]. Policy implications: The absence of harmonized measurement standards limits the ability to compare results across studies and regions, making it difficult to assess policy effectiveness or design targeted interventions. Establishing standardized, transparent, and internationally coordinated monitoring systems is identified as a critical gap for effective policy design and evaluation [DOC053::chunk::158]; [DOC095::chunk::79]. Final policy decisions should consider these scientific limitations. | AB7: 6071 | AC7: 070de68e-e8d1-4dc1-9884-da43fef7d91f
A8: Q03 | B8: Direct evidence retrieval | C8: Medium | D8: Transport / deposition | E8: What is the evidence for atmospheric transport and deposition of microplastics, and what does this imply for considering long-term pollution? | F8: DOC058 DOc035 DOc005 DOc023 DOC091 | G8: magnitues are not well established as well as estimate range by upto 4 orders of manigitue DOC059: "no one has yet published a comprehensive size distribution for microplastics smaller than 10 µm" | H8: seperates the quantitive findings from the qualittive ones and make refercne th oth range in orders of mangitude. And that the deposisition estiamtes are demandands on the models used | I8: DOC002::chunk::71; DOC014::chunk::223; DOC016::chunk::212; DOC095::chunk::78; DOC059::chunk::107; DOC106::chunk::137 | J8: none | K8: 172 | L8: 3.187 | M8: 1 | N8: 6 | O8: 0.00836 | P8: 2 | Q8: 2 | R8: 1 | S8: 2 | T8: 2 | U8: 1 | V8: 2 | W8: 21 | X8: =IF(COUNT(P8:V8)=0,"",SUM(P8:V8)) -> 12 | Y8: =IF(X8="","",X8/21) -> 0.57142857 | Z8: Searched once and stopped, so answered from the same material as everyone else. | AA8: **Scientific Evidence:** Multiple studies confirm that microplastics are present in the atmosphere across urban, rural, and remote regions, indicating significant potential for long-range atmospheric transport and deposition [DOC095::chunk::78]. Atmospheric transport is identified as a major pathway for microplastics to reach remote areas, including mountain catchments and the marine atmosphere [DOC002::chunk::71]; [DOC059::chunk::107]. Fibres and fragments are the most common forms detected, and deposition occurs via both dry and wet processes, influenced by wind, snowfall, and weathering [DOC095::chunk::78]. However, research is still in early stages, with insufficient standardized data on abundance, composition, and size distribution, especially in remote areas [DOC095::chunk::78]. There is agreement on the global reach of atmospheric microplastics, but limitations include non-standardized sampling and detection protocols, making cross-study comparisons difficult [DOC095::chunk::78]. **Possible Policy Implications:** The evidence suggests that microplastics should be considered as persistent atmospheric pollutants with potential for long-term, widespread environmental distribution [DOC095::chunk::78]. However, due to data gaps and methodological inconsistencies, further research is needed before establishing specific long-term pollution thresholds or regulatory measures. Final decisions should account for these uncertainties. | AB8: 3343 | AC8: 0929fb42-7c8a-473f-a93a-aa43d25355cd
A9: Q04 | B9: Direct evidence retrieval | C9: Medium | D9: Human health / exposure | E9: What evidence is there about human exposure to atmospheric microplastics, and what are the main limitations policymakers should be aware of? | F9: DOC017,DOC018 Doc 021(inhillantion) DOC046,DOC025,D0c043 (toxicoligy), DOC014 (evidance review). DOC063(microplasics in lung tissue). DOC0112,Doc113 (Uk indoor expsoure menasurments | G9: that there is insufficnet evdiance to acess the helth risks and there isnt an indefited relationships between quantities and health affects\. Exposure is given but harm isnt. That toxicoluge is on cells no peope. And could be work place realted not atmophere wedont know | H9: give clear evidance shoes there isnt a defined risk acessment to carry out and dsont convernt findings on animlas in human findings. as well as giving a good policy maker overview. | I9: DOC014::chunk::239; DOC095::chunk::74; DOC014::chunk::241; DOC033::chunk::2; DOC093::chunk::4; DOC035::chunk::6; DOC052::chunk::53; DOC021::chunk::266; DOC014::chunk::245; DOC018::chunk::3; DOC020::chunk::798 | J9: none | K9: 142 | L9: 3.625 | M9: 2 | N9: 11 | O9: 0.01208 | P9: 3 | Q9: 2 | R9: 1 | S9: 2 | T9: 3 | U9: 2 | V9: 2 | W9: 21 | X9: =IF(COUNT(P9:V9)=0,"",SUM(P9:V9)) -> 15 | Y9: =IF(X9="","",X9/21) -> 0.71428571 | Z9: Extra searching found the UK reports the others missed. | AA9: Scientific evidence shows that atmospheric microplastics (MPs) are present in urban and remote environments, with synthetic textile fibres being a dominant source [DOC033::chunk::2; DOC093::chunk::4]. Human exposure can occur via inhalation and dust ingestion, especially in urban areas where concentrations are higher [DOC095::chunk::74; DOC093::chunk::4; DOC035::chunk::6]. Microplastics have been detected in human lung tissue and are associated with respiratory symptoms in occupational settings with high exposures [DOC095::chunk::74; DOC018::chunk::3]. However, for the general population, direct epidemiological evidence of health effects from environmental exposure is lacking [DOC052::chunk::53; DOC018::chunk::3]. Major limitations include insufficient data on airborne MP concentrations, especially for inhalable size fractions, and a lack of harmonised measurement methods [DOC014::chunk::241; DOC018::chunk::3; DOC021::chunk::266]. Most exposure estimates are based on limited locations and crude methods, making quantitative risk assessment unreliable [DOC014::chunk::245; DOC021::chunk::266]. Policymakers should note these significant evidence gaps and uncertainties when considering potential health risks and interventions. | AB9: 5132 | AC9: 7376df3d-8895-4f85-8f53-e2d30866e71f
A10: Q05 | B10: Multi-source & cross-topic synthesis | C10: Medium | D10: Sources + transport | E10: What does the evidence suggest about interventions regarding the source-to-deposition pathway? | F10: DOC003,005,002 (sources of microplassitcs and the atomphere cycle) DOC034,058,029 (transport). DOC073,065,073(what the uk and eu is curnety doing DOc022, 108 (interviention modeling ) | G10: none of the papers actually rank the interventions they just give solutions as there is no review in the coupus, thre are different orders of mannuture in the transport sections so this needs to be comunicated clearly | H10: shows clearnly the different stages as well as keeping clear and traspanrtry to the souces. Keeping the actualy evideance of wahts going on sepreatate from the findings about possible interventions. Showuldn show where to intervene and diffent oiptions but not suggest a best option | I10: DOC014::chunk::240; DOC091::chunk::37; DOC014::chunk::49; DOC105::chunk::52; DOC038::chunk::77; DOC029::chunk::33; DOC002::chunk::71; DOC053::chunk::164; DOC043::chunk::62; DOC106::chunk::436; DOC059::chunk::107; DOC106::chunk::142; DOC059::chunk::131 | J10: none | K10: 185 | L10: 4.649 | M10: 3 | N10: 13 | O10: 0.01725 | P10: 2 | Q10: 2 | R10: 1 | S10: 2 | T10: 3 | U10: 2 | V10: 1 | W10: 21 | X10: =IF(COUNT(P10:V10)=0,"",SUM(P10:V10)) -> 13 | Y10: =IF(X10="","",X10/21) -> 0.61904762 | Z10: Three searches, little new from the last one. | AA10: **Scientific Evidence:** Atmospheric transport is a major pathway for microplastics (MPs) to reach remote and urban regions, with deposition rates on remote tropical islands similar to those in urban areas, indicating that few, if any, coastal ecosystems remain pristine with respect to MP contamination [DOC091::chunk::37]; [DOC002::chunk::71]; [DOC059::chunk::107]. MPs originate from diverse sources, including car tyres, plastic-based textiles, household dust, and sewage effluent, and are transported via wind, precipitation, and turbulence, often traveling thousands of kilometers [DOC014::chunk::49]; [DOC029::chunk::33]; [DOC038::chunk::77]. Modeling and back-tracing methods can help identify source regions and transport pathways, but the analysis of atmospheric MPs is still nascent, with significant gaps in understanding transport mechanisms, deposition processes, and source apportionment [DOC038::chunk::77]; [DOC029::chunk::33]. There is also a lack of standardized detection and quantification methods, which limits the assessment of intervention effectiveness [DOC053::chunk::164]. **Policy Implications:** Current evidence highlights the complexity of the source-to-deposition pathway and the need for interdisciplinary approaches and improved monitoring to inform interventions. However, the lack of standardized methods and data gaps limit the ability to design and evaluate targeted policies for atmospheric MPs [DOC053::chunk::164]; [DOC014::chunk::240]. Final policy decisions should consider these limitations. | AB10: 7418 | AC10: f38d4164-003a-459d-abe3-d4442736dadb
A11: Q06 | B11: Multi-source & cross-topic synthesis | C11: Hard | D11: Exposure + human health | E11: What does the current evidence on atmospheric microplastics suggest in terms of the human health impacts, and its relevance for policy consideration? | F11: DOC017, 018 (Committee on the Medical Effects of Air Pollutants ). DOC021(inhilantion). DOC014(Science Advice for Policy by European Academies review) DOC045, 025, 043 (toxicoligy) DOC063 ( Micorpstics in lungs) DOC0112,113 (Uk indoor expsoure menasurments | G11: comeap finds insufficne evidance to acess the health risks as there is no dose relatships. As well as Sepea finds no evidance of widespready risk however its from 2019 outdie courpus range | H11: give clear evidance shoes there isnt a defined risk acessment to carry out and dsont convernt findings on animlas in human findings. as well as giving a good policy maker overview. | I11: DOC014::chunk::239; DOC095::chunk::74; DOC052::chunk::12; DOC095::chunk::9; DOC017::chunk::17; DOC093::chunk::4; DOC021::chunk::24; DOC025::chunk::72; DOC106::chunk::411; DOC052::chunk::13; DOC002::chunk::2 | J11: none | K11: 207 | L11: 4.646 | M11: 3 | N11: 11 | O11: 0.01494 | P11: 2 | Q11: 2 | R11: 2 | S11: 2 | T11: 3 | U11: 2 | V11: 2 | W11: 21 | X11: =IF(COUNT(P11:V11)=0,"",SUM(P11:V11)) -> 15 | Y11: =IF(X11="","",X11/21) -> 0.71428571 | Z11: Finds a toxicity paper no one else reached. | AA11: **Scientific Evidence:** Current evidence indicates that atmospheric microplastics (AMPs) are widespread in urban, suburban, and even remote environments, exposing much of the global population to these particles [DOC093::chunk::4]; [DOC095::chunk::9]. Human exposure occurs primarily through inhalation and dust ingestion, with indoor dust being a significant source [DOC095::chunk::9]; [DOC095::chunk::74]. Microplastics have been detected in human lung tissue, and occupational studies link exposure to respiratory symptoms in workers [DOC095::chunk::74]. Toxicological studies suggest that inhaled microplastics may induce oxidative stress, inflammation, and cytotoxicity in lung tissue, but these findings are based on limited data, often using unrealistically high concentrations and poorly characterized particles, limiting their relevance to real-world exposures [DOC017::chunk::17]. There is broad agreement that data on exposure levels, health effects, and toxicological pathways are insufficient for robust risk assessment [DOC014::chunk::239]; [DOC021::chunk::24]; [DOC002::chunk::2]. Key gaps include standardized monitoring methods, quantification techniques, and understanding of long-range transport and deposition [DOC002::chunk::2]; [DOC052::chunk::12]. **Policy Relevance:** Given the incomplete and uncertain evidence base, policymakers should be aware that while there is potential for health impacts from atmospheric microplastics, current data are insufficient for quantitative risk assessment or for evaluating the effectiveness of specific interventions [DOC014::chunk::239]; [DOC017::chunk::17]. Further research and improved monitoring are needed before definitive policy actions can be justified. Final decisions remain with policymakers. | AB11: 6151 | AC11: 25e3c45f-f366-4760-b02c-7fae4bde1332
A12: Q07 | B12: Multi-source & cross-topic synthesis | C12: Hard | D12: Deposition + ecology | E12: How does atmospheric deposition cause atmospheric microplastics to reach ecosystems, and what remains uncertain? | F12: DOC027 ( desposition to wetlands) DOC049 (ecoligcal risks) DOC103, 104, 026 ( soil and plants) DOC105 (unknown aspects of plastic pollution) DOC050 , 062 (deposistion measruments) | G12: the coupus mainly focuses on deposisiton there isnt much evidance about the impact of this deposiston of microplastics on ecosystems | H12: must speerate the effects form the effects evidance . And must note that the concetations used in the lab soil expements is much higher than that was ovserved in the field.. | I12: DOC027::chunk::4; DOC095::chunk::69; DOC005::chunk::5; DOC014::chunk::110; DOC053::chunk::24; DOC027::chunk::6; DOC053::chunk::14; DOC049::chunk::73; DOC062::chunk::7; DOC053::chunk::110; DOC016::chunk::542 | J12: none | K12: 171 | L12: 3.834 | M12: 2 | N12: 11 | O12: 0.01171 | P12: 2 | Q12: 2 | R12: 2 | S12: 2 | T12: 3 | U12: 2 | V12: 2 | W12: 21 | X12: =IF(COUNT(P12:V12)=0,"",SUM(P12:V12)) -> 15 | Y12: =IF(X12="","",X12/21) -> 0.71428571 | Z12: Two new documents. Figures correct. | AA12: **Scientific Evidence:** Atmospheric deposition enables microplastics to reach ecosystems through both wet (rain, snow) and dry (settling) processes, allowing particles to travel long distances and deposit in remote areas, including glaciers and wetlands [DOC095::chunk::69]; [DOC027::chunk::4]; [DOC062::chunk::7]. Studies show that atmospheric pathways can contribute more microplastics to aquatic environments than wastewater or riverine sources, with wetlands acting as significant sinks [DOC027::chunk::4]. Microplastics are transported globally by wind and atmospheric currents, and their deposition rates vary widely, with estimates up to 700 particles m⁻²·d⁻¹ in remote regions [DOC005::chunk::5]. However, the mechanisms of emission, transport, and deposition—especially for different particle sizes—are not fully understood [DOC053::chunk::24]; [DOC005::chunk::5]. There is limited quantitative data on fluxes, spatial gradients, and the specific ecological risks posed by atmospheric microplastics, particularly regarding their fate and effects after deposition [DOC049::chunk::73]; [DOC014::chunk::110]; [DOC016::chunk::542]. **Policy Implications:** While evidence confirms atmospheric deposition as a major pathway for microplastics into ecosystems, significant uncertainties remain about sources, transport mechanisms, deposition patterns, and ecological impacts. Further research is needed to inform effective policy responses [DOC027::chunk::6]; [DOC053::chunk::24]; [DOC016::chunk::542]. | AB12: 4753 | AC12: 7da078ed-f263-43fa-a99b-9a52c6e7ec43
A13: Q08 | B13: Multi-source & cross-topic synthesis | C13: Hard | D13: Measurement + evidence interpretation | E13: How do differences in sampling and methods affect comparison of atmospheric microplastic evidence to inform policy? | F13: DOC109(chemical anlyais) DOC030 ( anlyalitcal methods) DOC111(anlyasis of deposition) DOC095(standarisation gaps) DOC017(Commitee of the medical effects of air polutants) DOC090, 061, 064 (sampling studies) | G13: there is no standissed method and comparitson is dificulrt as there is deiiffernt collection,processing andn alyltical methods across all of the studies | H13: explain the diffrenty methods, and not compairing figures from from the studdies directly as they are from diffent tecniques and there is no standised method and dosent recommend a montering method/ standards that’s not in the coupus. | I13: DOC033::chunk::31; DOC030::chunk::43; DOC003::chunk::7; DOC021::chunk::86; DOC006::chunk::15; DOC095::chunk::79 | J13: none | K13: 174 | L13: 4.135 | M13: 1 | N13: 6 | O13: 0.00642 | P13: 2 | Q13: 2 | R13: 2 | S13: 2 | T13: 3 | U13: 3 | V13: 2 | W13: 21 | X13: =IF(COUNT(P13:V13)=0,"",SUM(P13:V13)) -> 16 | Y13: =IF(X13="","",X13/21) -> 0.76190476 | Z13: Searched once and stopped, correctly. Restraint here is as telling as persistence. | AA13: Scientific evidence: There is broad agreement that differences in sampling and analytical methods significantly hinder the comparability of atmospheric microplastic (MP) studies. Variations in sampling techniques, analytical approaches, and reporting units make it difficult to compare results across studies or to relate findings to air quality guidelines and health effect thresholds [DOC003::chunk::7]; [DOC021::chunk::86]; [DOC030::chunk::43]; [DOC033::chunk::31]; [DOC095::chunk::79]. For example, some methods only detect MPs above certain sizes (often >10 or >50 μm), leaving the respirable fraction (<2.5 μm) largely unquantified [DOC021::chunk::86]; [DOC033::chunk::31]. Passive and active sampling methods each have strengths and limitations, and environmental factors such as weather can further affect results [DOC006::chunk::15]. The lack of standardized protocols for sampling, identification, and data reporting prevents reliable synthesis of evidence and robust risk assessment [DOC030::chunk::43]; [DOC095::chunk::79]. Policy implications: Due to these methodological inconsistencies and data gaps, current evidence is insufficient for direct comparison with regulatory air quality standards or for comprehensive risk assessment. Standardized methods are needed before policy decisions can be reliably informed by atmospheric microplastic data [DOC033::chunk::31]; [DOC095::chunk::79]. Final decisions remain with the policymaker. | AB13: 2279 | AC13: 7e78e014-ed90-471e-88b7-1aa646440d9d
A14: Q09 | B14: Conflicting evidence & comparison | C14: Medium | D14: Measurement / monitoring | E14: How much do reported concentrations of atmospheric microplastics differ between environments and why? | F14: DOC095 (spread) DOC090 (weser,germany cathcment) DOC061, 113 (humber UK Indoors and Outdoors) DOC112, (Birmingham Indoor air) DOC041, 051 (forest urban rural) DOC030, 109 ( Explain variation) | G14: much of the information in the coupus on this topic is mearly methodoligy and some of the reptored concentrations differ by upto a thousnad times. And the spectromatry and mass spectromatry results and not comparible as one gives how many the other how much. and spectornomy hasa. floor in hte sizes it can detect of around 10um as anyhting below this is not noticeable in most studies. | H14: Reoports a rang of different reuslts and making sure to state the differnces in methods as well as sepesrating the differances caused by the diffrent envroments from the differances in methods | I14: DOC095::chunk::41; DOC003::chunk::81; DOC095::chunk::63; DOC003::chunk::62; DOC024::chunk::17; DOC053::chunk::37 | J14: none | K14: 165 | L14: 2.701 | M14: 1 | N14: 6 | O14: 0.0076 | P14: 2 | Q14: 2 | R14: 2 | S14: 2 | T14: 2 | U14: 2 | V14: 2 | W14: 21 | X14: =IF(COUNT(P14:V14)=0,"",SUM(P14:V14)) -> 14 | Y14: =IF(X14="","",X14/21) -> 0.66666667 | Z14: Searched once. Figures correct. | AA14: **Scientific Evidence:** Reported concentrations of atmospheric microplastics are significantly higher indoors than outdoors. Studies show indoor air contains 6 to 6.5 times more microplastics than outdoor air, with indoor concentrations ranging from 1.0 to 60.0 fibres/m³ and outdoor concentrations from 0.3 to 1.5 fibres/m³, though some outdoor sites (e.g., Surabaya, Indonesia) report up to 174 particles/m³ [DOC095::chunk::41]; [DOC003::chunk::81]. The dominant size range is 100–300 μm, with fibres and fragments most common [DOC053::chunk::37]; [DOC095::chunk::63]. Indoor microplastics are linked to indoor sources and occupant activities, while outdoor concentrations are highest near industrial and urban areas [DOC053::chunk::37]. Outdoor microplastics are generally smaller and less variable than indoor ones [DOC003::chunk::81]; [DOC095::chunk::63]. Methodological differences and lack of standardization limit direct comparisons, though harmonization is improving [DOC095::chunk::41]. **Possible Policy Implications:** Evidence suggests indoor environments are a major source of atmospheric microplastics, and concentrations vary with proximity to sources and human activity. However, methodological limitations and data gaps remain, especially regarding standardization and global comparability. Final policy decisions should consider these uncertainties. | AB14: 2888 | AC14: eccfb758-fddc-4a1f-a955-424bbf80d0e2
A15: Q10 | B15: Conflicting evidence & comparison | C15: Hard | D15: Sources / intervention relevance | E15: How consistent is the evidence that tyre wear is a major source of atmospheric microplastics, and how reliable are current estimates of its contribution to the problem? | F15: DOC003, 109 (cover tyre wear) DOC005 (Emission figures) DOC034, 047, 038, 045 ( reviews that mention tyrewear) DOC022 (estimates tyre loss from trafic data) | G15: the estimates dissagreee with DOc003 saying 84% of airmbone plastics come from road use. Howevern doc 005 says 96Gg of micro plastics aare entering long range transport from tyres. But them DOC0109 notes that tyres are only 40-60% poylomer so what dos actually count as a micro plastic nedes to be considerd | H15: tyre ware needs to be mentiond as one of the major couases of atmopeheric micro plastics but that the soruces give confliction results int terms of estimates. | I15: DOC038::chunk::28; DOC035::chunk::33; DOC003::chunk::45; DOC077::chunk::79; DOC038::chunk::26; DOC022::chunk::131; DOC045::chunk::24; DOC106::chunk::30; DOC017::chunk::7; DOC035::chunk::41; DOC002::chunk::85; DOC005::chunk::62 | J15: none | K15: 186 | L15: 5.368 | M15: 3 | N15: 12 | O15: 0.01802 | P15: 2 | Q15: 2 | R15: 2 | S15: 2 | T15: 3 | U15: 2 | V15: 2 | W15: 21 | X15: =IF(COUNT(P15:V15)=0,"",SUM(P15:V15)) -> 15 | Y15: =IF(X15="","",X15/21) -> 0.71428571 | Z15: Fullest account of tyre wear, including how hard tyre dust is to identify. | AA15: **Scientific Evidence:** Multiple sources consistently identify tyre wear as a significant source of atmospheric microplastics (MPs). Tyre wear particles (TWPs) are recognized as a major contributor to airborne MPs globally, with estimates suggesting that 0.1–10% of generated tyre wear becomes airborne [DOC038::chunk::28], and up to 5% of tyre wear is aerosolized, amounting to approximately 146,000 tonnes per year in selected countries [DOC003::chunk::45]. Global estimates vary widely, with one study reporting 2,907,000 tonnes of airborne tyre wear annually [DOC003::chunk::45]. Tyre wear is also reported to constitute 0.1–10% of PM10 and 3–7% of PM2.5 in the atmosphere [DOC038::chunk::26]. However, there are methodological limitations: many studies do not distinguish tyre wear from other microplastics due to analytical challenges [DOC035::chunk::33], and there is a lack of empirical data on the fate and transport of TWPs [DOC045::chunk::24]. Ongoing research aims to address these gaps [DOC077::chunk::79]. **Policy Implications:** While evidence consistently points to tyre wear as a major source of atmospheric MPs, uncertainties in quantification and characterization limit the reliability of current estimates. Further research is needed to refine these estimates and inform effective interventions. Final decisions should consider these limitations [DOC017::chunk::7]. | AB15: 7641 | AC15: def242de-cf5e-4dcd-b57a-12242e3c0258
A16: Q11 | B16: Conflicting evidence & comparison | C16: Hard | D16: Transport / spatial scale | E16: What is agreed and what is disputed in the long-range transport of atmospheric microplastics, and how do transport estimates disagree in terms of scale? | F16: DOC058 (long term transport) DOC034 (remote region transport DOC005 (uncertantcys for transport and deposisiton) DOC029 (trasport in asia) DOC059 (atmopshertic Modeling) DOC095, 047 (Reviews) | G16: it is genrally agreed that trasport does occour to remote regions. But the sale is not this needs to be reflected in the answer | H16: it needs to show that trasport does occour even to remote rgions and make it clear that there is no definitive view on the scale. | I16: DOC005::chunk::21; DOC047::chunk::23; DOC058::chunk::0; DOC014::chunk::53; DOC035::chunk::34; DOC014::chunk::54; DOC058::chunk::1; DOC035::chunk::6; DOC052::chunk::50; DOC002::chunk::2 | J16: none | K16: 240 | L16: 4.992 | M16: 2 | N16: 10 | O16: 0.01238 | P16: 2 | Q16: 2 | R16: 2 | S16: 2 | T16: 3 | U16: 3 | V16: 2 | W16: 21 | X16: =IF(COUNT(P16:V16)=0,"",SUM(P16:V16)) -> 16 | Y16: =IF(X16="","",X16/21) -> 0.76190476 | Z16: Adds a point no one else made: nobody has measured over the oceans. | AA16: **Scientific Evidence:** There is broad agreement that atmospheric microplastics (AMPs) can undergo long-range transport, reaching remote regions such as Antarctica and the Southern Ocean [DOC058::chunk::0], [DOC058::chunk::1]. Multiple studies confirm that AMPs originate from diverse sources and are transported by wind, with morphology (e.g., fibers vs. fragments) influencing transport efficiency—fibers are transported more efficiently over long distances [DOC058::chunk::0]. The atmosphere is recognized as a rapid and significant pathway for microplastic movement between land, ocean, and remote environments [DOC047::chunk::23], [DOC002::chunk::2]. However, there are substantial uncertainties and disagreements regarding the scale of transport and deposition. Emission estimates for long-range transported microplastics vary widely, with some studies reporting global emissions from tire wear and braking at 96 [63 to 110] Gg·y⁻¹, while others estimate up to 284 (102 to 787) Gg·y⁻¹, depending on assumptions about particle size and transport efficiency [DOC005::chunk::21]. Methodological inconsistencies, such as differences in sampling, particle identification, and size cut-offs, further complicate cross-study comparisons and contribute to uncertainty in transport and deposition estimates [DOC052::chunk::50], [DOC002::chunk::2]. There is also a lack of direct atmospheric measurements, especially over oceans, and limited understanding of how meteorological variables affect transport in different environments [DOC035::chunk::34], [DOC014::chunk::53]. **Policy Implications:** While evidence supports the occurrence of long-range atmospheric transport of microplastics, the scale and dynamics remain highly uncertain due to methodological limitations and knowledge gaps. Further research and standardized monitoring are needed before robust regulatory decisions can be made [DOC002::chunk::2], [DOC052::chunk::50]. Final policy decisions should consider these uncertainties. | AB16: 4853 | AC16: 80ecf9fa-fdf6-49ab-99a4-96ff4d22beb8
A17: Q12 | B17: Conflicting evidence & comparison | C17: Hard | D17: UK relivance | E17: What existing UK policy instruments address microplastics, and do any of them cover atmospheric sources? | F17: DOC075 (packaging tax) DOC073 (Single Use bans) DOC072 (Microbeads) DOC084 Producer responcibilty) DOC078 (Air quality stratagy) DOC089 (Clean air zones) DOC077, 078, 082,088 (curnet uk strategys) | G17: there is a clear gap as ther is nothing in the coupus that links atmopsheric. As it does not fall under the efford to regualte particualte matter but ithis is mainly focused on pm 2.5 | H17: indentifyes a clear gap in the lesgisaltion | I17: DOC020::chunk::445; DOC035::chunk::2; DOC014::chunk::240; DOC059::chunk::1; DOC014::chunk::33; DOC035::chunk::6; DOC013::chunk::23; DOC022::chunk::336; DOC022::chunk::338; DOC062::chunk::8; DOC052::chunk::24 | J17: none | K17: 227 | L17: 5.571 | M17: 3 | N17: 11 | O17: 0.01451 | P17: 2 | Q17: 1 | R17: 2 | S17: 2 | T17: 3 | U17: 2 | V17: 2 | W17: 21 | X17: =IF(COUNT(P17:V17)=0,"",SUM(P17:V17)) -> 14 | Y17: =IF(X17="","",X17/21) -> 0.66666667 | Z17: Found a UK study no one else did. But lists international rules as UK ones. | AA17: Scientific Evidence: There is clear evidence that atmospheric microplastics are present in the UK, including in urban environments such as London, with deposition rates of 575–1008 microplastics/m²/day and a predominance of fibrous forms [DOC035::chunk::2]. Atmospheric transport enables microplastics to reach remote regions, and both local and long-range sources contribute to urban deposition [DOC035::chunk::6]; [DOC059::chunk::1]. However, the scientific literature highlights a paucity of evidence on the extent of atmospheric microplastic contamination and exposure in the UK, and notes significant variability in deposition rates due to differences in sampling and analytical methods [DOC062::chunk::8]. There is also a gap in systematic monitoring and targeted research on atmospheric microplastics, especially secondary microplastics from fragmentation, which are underrepresented in policy frameworks [DOC062::chunk::8]. Policy Evidence: Current UK policy instruments addressing microplastics primarily focus on aquatic and terrestrial pathways, such as bans or controls on intentionally added microplastics, measures to minimize pellet leakage, and support for wastewater treatment improvements [DOC013::chunk::23]; [DOC022::chunk::336]. There is no direct evidence that existing UK policies specifically target atmospheric microplastic sources or deposition. The need for comprehensive policy mixes, including research, monitoring, and enabling measures, is recognized, but atmospheric microplastics remain insufficiently addressed [DOC022::chunk::338]; [DOC062::chunk::8]. Limitations and Gaps: There is insufficient evidence of UK policy instruments explicitly covering atmospheric microplastics. Further research and policy development are needed to address this gap [DOC062::chunk::8]. Final policy decisions remain with the human policymaker. | AB17: 5951 | AC17: 0204a962-323a-49c9-a558-cb50fc7350cb
... A20: Q15 | B20: Evidence strength & uncertainty | C20: Hard | D20: Ecological impacts | E20: How strong is the evidence that atmospheric microplastic deposition has a detrimental ecological impact, and what evidence gaps limit policy action? | F20: DOC027 (wetland deposition), DOC050, 062 (deposition measurement) DOC049 (ecological risks) DOC036 (environmental fate and impacts) DOC103 (soil properties), DOC104 (soil carbon cycling. DOC026 (lettuce stress response), DOC105 (meta-analysis of known and unknown effects). | G20: bothe deposistona nd the effectson are both disgiussed and measured in the coupus however there isnt a study that recectaly links and compairs them | H20: well written and distuagised the differtnce from field observations and and lab stuidies. | I20: DOC035::chunk::36; DOC005::chunk::42; DOC014::chunk::241; DOC005::chunk::38; DOC014::chunk::9; DOC027::chunk::4; DOC053::chunk::14; DOC053::chunk::164; DOC027::chunk::58; DOC020::chunk::668; DOC049::chunk::33; DOC105::chunk::69; DOC027::chunk::59 | J20: none | K20: 168 | L20: 4.651 | M20: 3 | N20: 13 | O20: 0.01436 | P20: 2 | Q20: 2 | R20: 2 | S20: 2 | T20: 3 | U20: 2 | V20: 2 | W20: 21 | X20: =IF(COUNT(P20:V20)=0,"",SUM(P20:V20)) -> 15 | Y20: =IF(X20="","",X20/21) -> 0.71428571 | Z20: Reports that studies find effects in some cases and not others. | AA20: **Scientific Evidence:** There is evidence that atmospheric microplastic deposition occurs widely, including in urban environments and wetlands, with deposition rates increasing alongside plastic production and usage [DOC035::chunk::36]; [DOC027::chunk::4]. Microplastics have been shown to accumulate in water, biota, and sediments, potentially disrupting ecosystems and affecting water quality [DOC053::chunk::14]. Microcosm experiments suggest unique ecological effects, such as reduced connectivity in moss phyllosphere bacterial communities, which may impact host plant health [DOC027::chunk::59]. Some locations may already have environmental concentrations exceeding predicted no-effect levels, indicating possible local ecological risks [DOC014::chunk::241]. However, the overall evidence for widespread detrimental ecological impacts remains mixed, with studies reporting both detected and non-detected effects [DOC105::chunk::69]. **Evidence Gaps and Limitations:** Major gaps include limited understanding of long-term ecological impacts, lack of standardized detection and quantification methods, and insufficient data on exposure and effects across ecosystems [DOC053::chunk::164]; [DOC014::chunk::241]. Most studies are constrained by sampling methods and scale, and there is considerable uncertainty about thresholds for negative effects [DOC027::chunk::59]; [DOC005::chunk::42]. This uncertainty limits the ability to develop comprehensive, evidence-based policies. | AB20: 6036 | AC20: 9eda45a8-d013-408d-b1ba-17c658d88743
A21: Q16 | B21: Evidence strength & uncertainty | C21: Hard | D21: Transport | E21: Is there evidence that atmospheric microplastic concentrations are increasing? | H21: should keep the solid conclusions apart from the bits where the scale or the mechanism is still uncertain. | I21: DOC035::chunk::6; DOC093::chunk::4; DOC016::chunk::214; DOC059::chunk::60; DOC003::chunk::71; DOC016::chunk::69; DOC003::chunk::152; DOC059::chunk::32; DOC022::chunk::253; DOC106::chunk::55 | J21: none | K21: 177 | L21: 7.701 | M21: 2 | N21: 10 | O21: 0.01062 | P21: 2 | Q21: 3 | R21: 2 | S21: 2 | T21: 2 | U21: 3 | V21: 2 | W21: 21 | X21: =IF(COUNT(P21:V21)=0,"",SUM(P21:V21)) -> 16 | Y21: =IF(X21="","",X21/21) -> 0.76190476 | Z21: the addition of the peat information that was omited from the other ouutpts | AA21: Scientific evidence indicates that atmospheric microplastic concentrations are increasing. Temporal analyses of ombrotrophic peat cores show that microplastic deposition rates have risen substantially since the mid-20th century, with surface samples (representing recent years) containing much higher concentrations than deeper, older layers; the proportion of microplastic fibres has also increased over time [DOC003::chunk::152]. Modelling studies project that, with global plastic production expected to rise, atmospheric microplastic emissions and concentrations will likely continue to grow, especially in urban areas where sources such as tyre wear and textile fibres are concentrated [DOC059::chunk::60]. Observational data and models both show that microplastics are now ubiquitous in the atmosphere, including remote regions, due to atmospheric transport [DOC059::chunk::32]. However, there are significant data gaps, particularly regarding terrestrial and urban environments, and long-term monitoring is limited [DOC016::chunk::214]. Thus, while evidence supports an increasing trend, comprehensive global quantification remains incomplete. Policy implications: The evidence of increasing atmospheric microplastic concentrations, especially in urban areas, highlights the need for improved monitoring and further research to address knowledge gaps and assess potential risks [DOC016::chunk::214]. Final decisions remain with policymakers. | AB21: 4456 | AC21: ca1aefff-c073-40d9-9946-0f25e6636212
